Workbook

Sheet monthly_attribution
A1: portfolio | B1: month | C1: benchmark_rate | D1: long_trading_pnl | E1: short_trading_pnl | F1: txn_costs | G1: borrow_costs | H1: margin_interest | I1: base_total_costs | J1: reconciliation_other_costs | K1: total_costs | L1: net_pnl | M1: lp_mgmt_fee_2_20 | N1: lp_perf_fee_2_20 | O1: lp_total_fees | P1: net_pnl | Q1: fee_compounding_drag
A2: Diamond Creek Fund | B2: 2023-01 | C2: 0.0432 | D2: 6175027.7 | E2: -4928985.3 | F2: 13517.74 | G2: 10515.613 | H2: 53870.58 | I2: 77903.94 | J2: -261829.08 | K2: =F2+G2+H2+J2 -> -183925.15 | L2: =D2+E2-K2 -> 1429967.5 | M2: 0 | N2: 0 | O2: =M2+N2 -> 0 | P2: 1437504 | Q2: -7536.46 | R2: =D2+E2-K2 -> 1429967.5
A3: Diamond Creek Fund | B3: 2023-02 | C3: 0.0457 | D3: 1025707.2 | E3: -462037.04 | F3: 2805.43 | G3: 10769.092 | H3: 59607.03 | I3: 73181.54 | J3: 0 | K3: =F3+G3+H3+J3 -> 73181.552 | L3: =D3+E3-K3 -> 490488.64 | M3: 0 | N3: 0 | O3: =M3+N3 -> 0 | P3: 493073.7 | Q3: -2585.05
A4: Diamond Creek Fund | B4: 2023-03 | C4: 0.0482 | D4: 4277165.1 | E4: -3408038.4 | F4: 14776.34 | G4: 13421.048 | H4: 76475.04 | I4: 104672.43 | J4: 0 | K4: =F4+G4+H4+J4 -> 104672.43 | L4: =D4+E4-K4 -> 764454.23 | M4: 50000 | N4: 389277 | O4: =M4+N4 -> 439277 | P4: 315055.72 | Q4: -51761.82
A5: Diamond Creek Fund | B5: 2023-04 | C5: 0.0481 | D5: -377747.97 | E5: 522858.91 | F5: 1740.26 | G5: 10789.463 | H5: 68438.98 | I5: 80968.71 | J5: -0.02 | K5: =F5+G5+H5+J5 -> 80968.683 | L5: =D5+E5-K5 -> 64142.257 | M5: 0 | N5: 0 | O5: =M5+N5 -> 0 | P5: 638.92 | Q5: 63503.32
A6: Diamond Creek Fund | B6: 2023-05 | C6: 0.0507 | D6: 4177917.5 | E6: -3020017.6 | F6: 2089.41 | G6: 12230.27 | H6: 86318.25 | I6: 100637.93 | J6: 0 | K6: =F6+G6+H6+J6 -> 100637.93 | L6: =D6+E6-K6 -> 1057261.9 | M6: 0 | N6: 0 | O6: =M6+N6 -> 0 | P6: 1019760.6 | Q6: 37501.38
A7: Diamond Creek Fund | B7: 2023-06 | C7: 0.0507 | D7: 3089532.9 | E7: -2282650.7 | F7: 12564.01 | G7: 13833.451 | H7: 88452.93 | I7: 114850.4 | J7: -0.02 | K7: =F7+G7+H7+J7 -> 114850.37 | L7: =D7+E7-K7 -> 692031.9 | M7: 63177.83 | N7: 362006.86 | O7: =M7+N7 -> 425184.69 | P7: 367851.91 | Q7: -37133.08
A8: Diamond Creek Fund | B8: 2023-07 | C8: 0.0532 | D8: 4655036.3 | E8: -3620840.6 | F8: 9830.95 | G8: 15332.878 | H8: 90902.94 | I8: 116066.77 | J8: -0.01 | K8: =F8+G8+H8+J8 -> 116066.76 | L8: =D8+E8-K8 -> 918128.96 | M8: 0 | N8: 0 | O8: =M8+N8 -> 0 | P8: 794017.05 | Q8: 124111.91
A9: Diamond Creek Fund | B9: 2023-08 | C9: 0.0532 | D9: -1574959.5 | E9: 1462011.9 | F9: 7841 | G9: 15891.272 | H9: 103551.64 | I9: 127283.91 | J9: 0.01 | K9: =F9+G9+H9+J9 -> 127283.92 | L9: =D9+E9-K9 -> -240231.49 | M9: 0 | N9: 0 | O9: =M9+N9 -> 0 | P9: -225593.94 | Q9: -14637.55
A10: Diamond Creek Fund | B10: 2023-09 | C10: 0.0532 | D10: -2650360.6 | E10: 2388335.4 | F10: 12320.72 | G10: 14686.008 | H10: 98059.74 | I10: 125066.46 | J10: -3201.85 | K10: =F10+G10+H10+J10 -> 121864.62 | L10: =D10+E10-K10 -> -383889.79 | M10: 71885.98 | N10: 51919.49 | O10: =M10+N10 -> 123805.47 | P10: -398220.9 | Q10: -95088.15
A11: Diamond Creek Fund | B11: 2023-10 | C11: 0.0532 | D11: -1089517.1 | E11: 1165627.6 | F11: 5396.02 | G11: 15364.674 | H11: 103212.84 | I11: 123973.53 | J11: -785.89 | K11: =F11+G11+H11+J11 -> 123187.64 | L11: =D11+E11-K11 -> -47077.104 | M11: 0 | N11: 0 | O11: =M11+N11 -> 0 | P11: -112888.14 | Q11: 65811.04
A12: Diamond Creek Fund | B12: 2023-11 | C12: 0.0532 | D12: 6656629.5 | E12: -5301135.2 | F12: 16198.97 | G12: 20683.13 | H12: 102585.16 | I12: 139467.26 | J12: 0.02 | K12: =F12+G12+H12+J12 -> 139467.28 | L12: =D12+E12-K12 -> 1216027 | M12: 0 | N12: 0 | O12: =M12+N12 -> 0 | P12: 1133127.2 | Q12: 82899.79
A13: Diamond Creek Fund | B13: 2023-12 | C13: 0.0532 | D13: 3916545.9 | E13: -2929109.4 | F13: 11133.69 | G13: 22636.559 | H13: 102413.47 | I13: 136183.72 | J13: 0 | K13: =F13+G13+H13+J13 -> 136183.72 | L13: =D13+E13-K13 -> 851252.78 | M13: 72982.28 | N13: 463660.22 | O13: =M13+N13 -> 536642.5 | P13: 463321.1 | Q13: -13300.61
A14: Diamond Creek Fund | B14: 2024-01 | C14: 0.0532 | D14: -305043.63 | E14: 667084.87 | F14: 11515.75 | G14: 20199.381 | H14: 106895.75 | I14: 138610.89 | J14: 2611.72 | K14: =F14+G14+H14+J14 -> 141222.6 | L14: =D14+E14-K14 -> 220818.64 | M14: 0 | N14: 0 | O14: =M14+N14 -> 0 | P14: 123973 | Q14: 96845.63
... A40: Diamond Creek Fund | B40: 2026-03 | C40: 0.0364 | D40: -2959797.9 | E40: 4491161.7 | F40: 48535.58 | G40: 251282.01 | H40: 142831.65 | I40: 442649.23 | J40: 36.08 | K40: =F40+G40+H40+J40 -> 442685.32 | L40: =D40+E40-K40 -> 1088678.5 | M40: 118026.44 | N40: 684444.22 | O40: =M40+N40 -> 802470.66 | P40: 888323.84 | Q40: 82328.2
D41: =SUM(D2:D40) -> 67525037 | E41: =SUM(E2:E40) -> -41496889 | F41: =SUM(F2:F40) -> 977946.19 | G41: =SUM(G2:G40) -> 2426923.6 | H41: =SUM(H2:H40) -> 4109596.1 | I41: =SUM(I2:I40) -> 7514465.9 | J41: =SUM(J2:J40) -> -280869.33 | K41: =SUM(K2:K40) -> 7233596.6 | ... N41: =SUM(N2:N40) -> 4193098 | O41: =M41+N41 -> 5341976 | P41: =SUM(P2:P40) -> 13452575

Sheet summary
A1: portfolio | B1: long_trading_pnl | C1: short_trading_pnl | D1: txn_costs_paid | E1: borrow_and_short_sale_rebate | F1: margin_interest | G1: total_costs | H1: reconciliation_other_costs | I1: total_costs | J1: net_pnl | K1: lp_mgmt_fee_2_20 | L1: lp_perf_fee_2_20 | M1: lp_total_fee_2_20 | N1: net_pnl_after_2_20
A2: Diamond Creek Fund | B2: =SUM(monthly_attribution!D2:D40) -> 67525037 | C2: =SUM(monthly_attribution!E2:E40) -> -41496889 | D2: =SUM(monthly_attribution!F2:F40) -> 977946.19 | E2: =SUM(monthly_attribution!G2:G40) -> 2426923.6 | F2: =SUM(monthly_attribution!H2:H40) -> 4109596.1 | G2: =SUM(monthly_attribution!I2:I40) -> 7514465.9 | H2: =SUM(monthly_attribution!J2:J40) -> -280869.33 | I2: =SUM(monthly_attribution!K2:K40) -> 7233596.6 | J2: =B2+C2-I2 -> 18794552 | K2: =SUM(monthly_attribution!M2:M40) -> 1148878 | L2: =SUM(monthly_attribution!N2:N40) -> 4193098 | M2: =K2+L2 -> 5341976 | N2: =J2-M2 -> 13452576
I3: =D2+E2+F2+H2 -> 7233596.6

Sheet daily_pnl_active_pairs
A1: date | B1: net_pnl_before_lp_fees | C1: active_pairs
A2: 44929 | B2: 0 | C2: 26
A3: 44930 | B3: 258659.35 | C3: 26
A4: 44931 | B4: -177017.7 | C4: 26
A5: 44932 | B5: 137451.17 | C5: 26
A6: 44935 | B6: 162639.96 | C6: 26
A7: 44936 | B7: 196102.83 | C7: 26
A8: 44937 | B8: 71240.65 | C8: 26
A9: 44938 | B9: 110098.36 | C9: 26
A10: 44939 | B10: 95583.98 | C10: 26
A11: 44943 | B11: 121405.74 | C11: 26
A12: 44944 | B12: -124165.81 | C12: 26
A13: 44945 | B13: -41244.9 | C13: 26
... A21: 44957 | B21: 174193.43 | C21: 26
A22: 44958 | B22: 270193.2 | C22: 26 | D22: =SUM(B2:B21) -> 1429967.5
A23: 44959 | B23: 608836.25 | C23: 26
A24: 44960 | B24: -186573.28 | C24: 26
A25: 44963 | B25: -21297.39 | C25: 26
A26: 44964 | B26: 106372.46 | C26: 26
A27: 44965 | B27: -142451.41 | C27: 26
A28: 44966 | B28: -225808.82 | C28: 26
A29: 44967 | B29: -107154.8 | C29: 26
A30: 44970 | B30: 67900.13 | C30: 26
A31: 44971 | B31: 111263.32 | C31: 26
A32: 44972 | B32: 159393.06 | C32: 26
A33: 44973 | B33: -157287.65 | C33: 26
A34: 44974 | B34: -60539.67 | C34: 26
... A814: 46112 | B814: 275898.08 | C814: 266
B815: =SUM(B2:B814) -> 18794551
