Workbook

Sheet ALL_PAIRS
A1: date | B1: etf | C1: under | D1: Underlying Price | E1: ETF Price | F1: long_sh | G1: short_sh | H1: long_notional_usd | I1: short_notional_usd | J1: gross_notional_usd | K1: borrow_rate_annual | L1: daily_long_pnl_usd | M1: daily_short_pnl_usd | N1: daily_borrow_cost_usd | O1: is_rebal | P1: cum_borrow_cost_usd | Q1: fed_funds_rate | R1: daily_txn_cost_usd | S1: daily_pair_net_pnl_usd
A2: 44929 | B2: AAPB | C2: AAPL | D2: 123.09602 | E2: 11.663906 | F2: 9028 | G2: -47878 | H2: =D2*F2 | I2: =E2*G2 | J2: =H2-I2 | K2: -0.005 | L2: 0 | M2: 0 | N2: =-I2*K2/252 | O2: 1 | P2: -11.080248 | Q2: 0.0432 | R2: 0 | S2: -11.080248
A3: 44929 | B3: AAPU | C3: AAPL | D3: 123.09602 | E3: 12.151525 | F3: 7633 | G3: -38936 | H3: =D3*F3 | I3: =E3*G3 | J3: =H3-I3 | K3: 0.02 | L3: 0 | M3: 0 | N3: =-I3*K3/252 | O3: 1 | P3: 37.55014 | Q3: 0.0432 | R3: 0 | S3: 37.55014
A4: 44929 | B4: AMZU | C4: AMZN | D4: 85.82 | E4: 11.52647 | F4: 27599 | G4: -103312 | H4: =D4*F4 | I4: =E4*G4 | J4: =H4-I4 | K4: -0.0025 | L4: 0 | M4: 0 | N4: =-I4*K4/252 | O4: 1 | P4: -11.813717 | Q4: 0.0432 | R4: 0 | S4: -11.813717
A5: 44929 | B5: TARK | C5: ARKK | D5: 30.208069 | E5: 15.614188 | F5: 20537 | G5: -20077 | H5: =D5*F5 | I5: =E5*G5 | J5: =H5-I5 | K5: -0.02 | L5: 0 | M5: 0 | N5: =-I5*K5/252 | O5: 1 | P5: -24.879846 | Q5: 0.0432 | R5: 0 | S5: -24.879846
A6: 44929 | B6: CHAU | C6: ASHR | D6: 26.669592 | E6: 18.896013 | F6: 5713 | G6: -4099 | H6: =D6*F6 | I6: =E6*G6 | J6: =H6-I6 | K6: -0.01 | L6: 0 | M6: 0 | N6: =-I6*K6/252 | O6: 1 | P6: -3.0736015 | Q6: 0.0432 | R6: 0 | S6: -3.0736015
A7: 44929 | B7: BABX | C7: BABA | D7: 87.352951 | E7: 26.02 | F7: 5330 | G7: -8920 | H7: =D7*F7 | I7: =E7*G7 | J7: =H7-I7 | K7: -0.0275 | L7: 0 | M7: 0 | N7: =-I7*K7/252 | O7: 1 | P7: -25.328199 | Q7: 0.0432 | R7: 0 | S7: -25.328199
A8: 44929 | B8: CONL | C8: COIN | D8: 33.599998 | E8: 4.2295198 | F8: 98778 | G8: -394919 | H8: =D8*F8 | I8: =E8*G8 | J8: =H8-I8 | K8: 0.03 | L8: 0 | M8: 0 | N8: =-I8*K8/252 | O8: 1 | P8: 198.84735 | Q8: 0.0432 | R8: 0 | S8: 198.84735
A9: 44929 | B9: MEXX | C9: EWW | D9: 45.605125 | E9: 16.087936 | F9: 9067 | G9: -8695 | H9: =D9*F9 | I9: =E9*G9 | J9: =H9-I9 | K9: 0.0075 | L9: 0 | M9: 0 | N9: =-I9*K9/252 | O9: 1 | P9: 4.1632324 | Q9: 0.0432 | R9: 0 | S9: 4.1632324
A10: 44929 | B10: KORU | C10: EWY | D10: 51.599609 | E10: 66.1492 | F10: 12826 | G10: -3410 | H10: =D10*F10 | I10: =E10*G10 | J10: =H10-I10 | K10: 0.0225 | L10: 0 | M10: 0 | N10: =-I10*K10/252 | O10: 1 | P10: 20.140069 | Q10: 0.0432 | R10: 0 | S10: 20.140069
A11: 44929 | B11: YINN | C11: FXI | D11: 27.235073 | E11: 47.690964 | F11: 35048 | G11: -6728 | H11: =D11*F11 | I11: =E11*G11 | J11: =H11-I11 | K11: -0.02 | L11: 0 | M11: 0 | N11: =-I11*K11/252 | O11: 1 | P11: -25.465461 | Q11: 0.0432 | R11: 0 | S11: -25.465461
A12: 44929 | B12: JNUG | C12: GDXJ | D12: 34.869011 | E12: 36.153866 | F12: 13873 | G12: -6778 | H12: =D12*F12 | I12: =E12*G12 | J12: =H12-I12 | K12: -0.005 | L12: 0 | M12: 0 | N12: =-I12*K12/252 | O12: 1 | P12: -4.8621211 | Q12: 0.0432 | R12: 0 | S12: -4.8621211
A13: 44929 | B13: GDXU | C13: GDX | D13: 28.63427 | E13: 46.52 | F13: 53192 | G13: -10760 | H13: =D13*F13 | I13: =E13*G13 | J13: =H13-I13 | K13: -0.005 | L13: 0 | M13: 0 | N13: =-I13*K13/252 | O13: 1 | P13: -9.9316509 | Q13: 0.0432 | R13: 0 | S13: -9.9316509
... A521: 44957 | B521: GUSH | C521: XOP | D521: 130.05548 | E521: 35.576096 | F521: 3135 | G521: -5607 | H521: =D521*F521 | I521: =E521*G521 | J521: =H521-I521 | K521: -0.01 | L521: 6189.4437 | M521: -6096.2949 | N521: =-I521*K521/252 | O521: 0 | P521: -156.37432 | Q521: 0.0432 | R521: 0 | S521: 85.233046

Sheet AAPL_AAPB
A1: date | B1: etf | C1: under | D1: AAPL Price | E1: AAPB Price | F1: long_sh | G1: short_sh | H1: long_notional_usd | I1: short_notional_usd | J1: gross_notional_usd | K1: borrow_rate_annual | L1: daily_long_pnl_usd | M1: daily_short_pnl_usd | N1: daily_borrow_cost_usd | O1: is_rebal | P1: cum_borrow_cost_usd
A2: 44929 | B2: AAPB | C2: AAPL | D2: 123.09602 | E2: 11.663906 | F2: 9028 | G2: -47878 | H2: =D2*F2 | I2: =E2*G2 | J2: =H2-I2 | K2: -0.005 | L2: 0 | M2: 0 | N2: =-I2*K2/252 | O2: 1 | P2: =SUM($N$2:N2)
A3: 44930 | B3: AAPB | C3: AAPL | D3: 124.36566 | E3: 11.826264 | F3: 9028 | G3: -47878 | H3: =D3*F3 | I3: =E3*G3 | J3: =H3-I3 | K3: -0.005 | L3: 0 | M3: 0 | N3: =-I3*K3/252 | O3: 0 | P3: =SUM($N$2:N3)
A4: 44931 | B4: AAPB | C4: AAPL | D4: 123.04681 | E4: 11.642097 | F4: 9028 | G4: -47878 | H4: =D4*F4 | I4: =E4*G4 | J4: =H4-I4 | K4: -0.005 | L4: -11906.557 | M4: 8817.5432 | N4: =-I4*K4/252 | O4: 0 | P4: =SUM($N$2:N4)
A5: 44932 | B5: AAPB | C5: AAPL | D5: 127.57419 | E5: 12.354533 | F5: 9028 | G5: -47878 | H5: =D5*F5 | I5: =E5*G5 | J5: =H5-I5 | K5: -0.005 | L5: 40873.135 | M5: -34109.998 | N5: =-I5*K5/252 | O5: 1 | P5: =SUM($N$2:N5)
A6: 44935 | B6: AAPB | C6: AAPL | D6: 128.09584 | E6: 12.463579 | F6: 9028 | G6: -47878 | H6: =D6*F6 | I6: =E6*G6 | J6: =H6-I6 | K6: -0.005 | L6: 4709.4763 | M6: -5220.9035 | N6: =-I6*K6/252 | O6: 0 | P6: =SUM($N$2:N6)
A7: 44936 | B7: AAPB | C7: AAPL | D7: 128.66672 | E7: 12.568586 | F7: 9028 | G7: -47878 | H7: =D7*F7 | I7: =E7*G7 | J7: =H7-I7 | K7: -0.005 | L7: 5153.8782 | M7: -5027.5334 | N7: =-I7*K7/252 | O7: 0 | P7: =SUM($N$2:N7)
A8: 44937 | B8: AAPB | C8: AAPL | D8: 131.38316 | E8: 12.972461 | F8: 9028 | G8: -47878 | H8: =D8*F8 | I8: =E8*G8 | J8: =H8-I8 | K8: -0.005 | L8: 24524.074 | M8: -19336.698 | N8: =-I8*K8/252 | O8: 0 | P8: =SUM($N$2:N8)
A9: 44938 | B9: AAPB | C9: AAPL | D9: 131.30441 | E9: 12.983769 | F9: 9028 | G9: -47878 | H9: =D9*F9 | I9: =E9*G9 | J9: =H9-I9 | K9: -0.005 | L9: -710.96051 | M9: -541.4365 | N9: =-I9*K9/252 | O9: 0 | P9: =SUM($N$2:N9)
A10: 44939 | B10: AAPB | C10: AAPL | D10: 132.63307 | E10: 13.198631 | F10: 9028 | G10: -47878 | H10: =D10*F10 | I10: =E10*G10 | J10: =H10-I10 | K10: -0.005 | L10: 11995.134 | M10: -10287.157 | N10: =-I10*K10/252 | O10: 1 | P10: =SUM($N$2:N10)
A11: 44943 | B11: AAPB | C11: AAPL | D11: 133.79445 | E11: 13.384414 | F11: 9057 | G11: -45734 | H11: =D11*F11 | I11: =E11*G11 | J11: =H11-I11 | K11: -0.005 | L11: 10518.591 | M11: -8496.5738 | N11: =-I11*K11/252 | O11: 0 | P11: =SUM($N$2:N11)
A12: 44944 | B12: AAPB | C12: AAPL | D12: 133.07597 | E12: 13.279407 | F12: 9057 | G12: -45734 | H12: =D12*F12 | I12: =E12*G12 | J12: =H12-I12 | K12: -0.005 | L12: -6507.2312 | M12: 4802.398 | N12: =-I12*K12/252 | O12: 0 | P12: =SUM($N$2:N12)
A13: 44945 | B13: AAPB | C13: AAPL | D13: 133.13504 | E13: 13.267289 | F13: 9057 | G13: -45734 | H13: =D13*F13 | I13: =E13*G13 | J13: =H13-I13 | K13: -0.005 | L13: 534.96776 | M13: 554.17653 | N13: =-I13*K13/252 | O13: 0 | P13: =SUM($N$2:N13)
... A21: 44957 | B21: AAPB | C21: AAPL | D21: 142.01265 | E21: 14.781819 | F21: 8874 | G21: -42412 | H21: =D21*F21 | I21: =E21*G21 | J21: =H21-I21 | K21: -0.005 | L21: 11266.497 | M21: -7879.3641 | N21: =-I21*K21/252 | O21: 0 | P21: =SUM($N$2:N21)

Sheet AAPL_AAPU
A1: date | B1: etf | C1: under | D1: AAPL Price | E1: AAPU Price | F1: long_sh | G1: short_sh | H1: long_notional_usd | I1: short_notional_usd | J1: gross_notional_usd | K1: borrow_rate_annual | L1: daily_long_pnl_usd | M1: daily_short_pnl_usd | N1: daily_borrow_cost_usd | O1: is_rebal | P1: cum_borrow_cost_usd
A2: 44929 | B2: AAPU | C2: AAPL | D2: 123.09602 | E2: 12.151525 | F2: 7633 | G2: -38936 | H2: =D2*F2 | I2: =E2*G2 | J2: =H2-I2 | K2: 0.02 | L2: 0 | M2: 0 | N2: =-I2*K2/252 | O2: 1 | P2: =SUM($N$2:N2)
A3: 44930 | B3: AAPU | C3: AAPL | D3: 124.36566 | E3: 12.34465 | F3: 7633 | G3: -38936 | H3: =D3*F3 | I3: =E3*G3 | J3: =H3-I3 | K3: 0.02 | L3: 0 | M3: 0 | N3: =-I3*K3/252 | O3: 0 | P3: =SUM($N$2:N3)
A4: 44931 | B4: AAPU | C4: AAPL | D4: 123.04681 | E4: 12.143798 | F4: 7633 | G4: -38936 | H4: =D4*F4 | I4: =E4*G4 | J4: =H4-I4 | K4: 0.02 | L4: -10066.764 | M4: 7820.3888 | N4: =-I4*K4/252 | O4: 0 | P4: =SUM($N$2:N4)
A5: 44932 | B5: AAPU | C5: AAPL | D5: 127.57419 | E5: 12.784979 | F5: 7633 | G5: -38936 | H5: =D5*F5 | I5: =E5*G5 | J5: =H5-I5 | K5: 0.02 | L5: 34557.448 | M5: -24965.023 | N5: =-I5*K5/252 | O5: 1 | P5: =SUM($N$2:N5)
A6: 44935 | B6: AAPU | C6: AAPL | D6: 128.09584 | E6: 12.877678 | F6: 7633 | G6: -38936 | H6: =D6*F6 | I6: =E6*G6 | J6: =H6-I6 | K6: 0.02 | L6: 3981.7714 | M6: -3609.3302 | N6: =-I6*K6/252 | O6: 0 | P6: =SUM($N$2:N6)
A7: 44936 | B7: AAPU | C7: AAPL | D7: 128.66672 | E7: 12.97038 | F7: 7633 | G7: -38936 | H7: =D7*F7 | I7: =E7*G7 | J7: =H7-I7 | K7: 0.02 | L7: 4357.5047 | M7: -3609.4416 | N7: =-I7*K7/252 | O7: 0 | P7: =SUM($N$2:N7)
A8: 44937 | B8: AAPU | C8: AAPL | D8: 131.38316 | E8: 13.356634 | F8: 7633 | G8: -38936 | H8: =D8*F8 | I8: =E8*G8 | J8: =H8-I8 | K8: 0.02 | L8: 20734.632 | M8: -15039.198 | N8: =-I8*K8/252 | O8: 0 | P8: =SUM($N$2:N8)
A9: 44938 | B9: AAPU | C9: AAPL | D9: 131.30441 | E9: 13.356634 | F9: 7633 | G9: -38936 | H9: =D9*F9 | I9: =E9*G9 | J9: =H9-I9 | K9: 0.02 | L9: -601.10341 | M9: 0 | N9: =-I9*K9/252 | O9: 0 | P9: =SUM($N$2:N9)
A10: 44939 | B10: AAPU | C10: AAPL | D10: 132.63307 | E10: 13.51886 | F10: 7633 | G10: -38936 | H10: =D10*F10 | I10: =E10*G10 | J10: =H10-I10 | K10: 0.02 | L10: 10141.655 | M10: -6316.4208 | N10: =-I10*K10/252 | O10: 1 | P10: =SUM($N$2:N10)
A11: 44943 | B11: AAPU | C11: AAPL | D11: 133.79445 | E11: 13.719712 | F11: 7658 | G11: -37829 | H11: =D11*F11 | I11: =E11*G11 | J11: =H11-I11 | K11: 0.02 | L11: 8893.8247 | M11: -7598.0452 | N11: =-I11*K11/252 | O11: 0 | P11: =SUM($N$2:N11)
A12: 44944 | B12: AAPU | C12: AAPL | D12: 133.07597 | E12: 13.59611 | F12: 7658 | G12: -37829 | H12: =D12*F12 | I12: =E12*G12 | J12: =H12-I12 | K12: 0.02 | L12: -5502.0842 | M12: 4675.7368 | N12: =-I12*K12/252 | O12: 0 | P12: =SUM($N$2:N12)
A13: 44945 | B13: AAPU | C13: AAPL | D13: 133.13504 | E13: 13.619286 | F13: 7658 | G13: -37829 | H13: =D13*F13 | I13: =E13*G13 | J13: =H13-I13 | K13: 0.02 | L13: 452.33334 | M13: -876.69614 | N13: =-I13*K13/252 | O13: 0 | P13: =SUM($N$2:N13)
... A21: 44957 | B21: AAPU | C21: AAPL | D21: 142.01265 | E21: 14.963447 | F21: 7503 | G21: -35693 | H21: =D21*F21 | I21: =E21*G21 | J21: =H21-I21 | K21: 0.02 | L21: 9525.8654 | M21: -7444.6764 | N21: =-I21*K21/252 | O21: 0 | P21: =SUM($N$2:N21)

Sheet AMZN_AMZU
A1: date | B1: etf | C1: under | D1: AMZN Price | E1: AMZU Price | F1: long_sh | G1: short_sh | H1: long_notional_usd | I1: short_notional_usd | J1: gross_notional_usd | K1: borrow_rate_annual | L1: daily_long_pnl_usd | M1: daily_short_pnl_usd | N1: daily_borrow_cost_usd | O1: is_rebal | P1: cum_borrow_cost_usd
A2: 44929 | B2: AMZU | C2: AMZN | D2: 85.82 | E2: 11.52647 | F2: 27599 | G2: -103312 | H2: =D2*F2 | I2: =E2*G2 | J2: =H2-I2 | K2: -0.0025 | L2: 0 | M2: 0 | N2: =-I2*K2/252 | O2: 1 | P2: =SUM($N$2:N2)
A3: 44930 | B3: AMZU | C3: AMZN | D3: 85.139999 | E3: 11.367292 | F3: 27599 | G3: -103312 | H3: =D3*F3 | I3: =E3*G3 | J3: =H3-I3 | K3: -0.0025 | L3: 0 | M3: 0 | N3: =-I3*K3/252 | O3: 0 | P3: =SUM($N$2:N3)
A4: 44931 | B4: AMZU | C4: AMZN | D4: 83.120003 | E4: 10.969353 | F4: 27599 | G4: -103312 | H4: =D4*F4 | I4: =E4*G4 | J4: =H4-I4 | K4: -0.0025 | L4: -55749.887 | M4: 41111.944 | N4: =-I4*K4/252 | O4: 0 | P4: =SUM($N$2:N4)
A5: 44932 | B5: AMZU | C5: AMZN | D5: 86.080002 | E5: 11.537718 | F5: 27599 | G5: -103312 | H5: =D5*F5 | I5: =E5*G5 | J5: =H5-I5 | K5: -0.0025 | L5: 81693.015 | M5: -58718.935 | N5: =-I5*K5/252 | O5: 1 | P5: =SUM($N$2:N5)
A6: 44935 | B6: AMZU | C6: AMZN | D6: 87.360001 | E6: 11.817143 | F6: 27599 | G6: -103312 | H6: =D6*F6 | I6: =E6*G6 | J6: =H6-I6 | K6: -0.0025 | L6: 35326.686 | M6: -28868.02 | N6: =-I6*K6/252 | O6: 0 | P6: =SUM($N$2:N6)
A7: 44936 | B7: AMZU | C7: AMZN | D7: 89.870003 | E7: 12.327546 | F7: 27599 | G7: -103312 | H7: =D7*F7 | I7: =E7*G7 | J7: =H7-I7 | K7: -0.0025 | L7: 69273.549 | M7: -52730.722 | N7: =-I7*K7/252 | O7: 0 | P7: =SUM($N$2:N7)
A8: 44937 | B8: AMZU | C8: AMZN | D8: 95.089996 | E8: 13.400256 | F8: 27599 | G8: -103312 | H8: =D8*F8 | I8: =E8*G8 | J8: =H8-I8 | K8: -0.0025 | L8: 144066.6 | M8: -110823.82 | N8: =-I8*K8/252 | O8: 0 | P8: =SUM($N$2:N8)
A9: 44938 | B9: AMZU | C9: AMZN | D9: 95.269997 | E9: 13.409775 | F9: 27599 | G9: -103312 | H9: =D9*F9 | I9: =E9*G9 | J9: =H9-I9 | K9: -0.0025 | L9: 4967.8284 | M9: -983.38802 | N9: =-I9*K9/252 | O9: 0 | P9: =SUM($N$2:N9)
A10: 44939 | B10: AMZU | C10: AMZN | D10: 98.120003 | E10: 14.023122 | F10: 27599 | G10: -103312 | H10: =D10*F10 | I10: =E10*G10 | J10: =H10-I10 | K10: -0.0025 | L10: 78657.318 | M10: -63366.111 | N10: =-I10*K10/252 | O10: 1 | P10: =SUM($N$2:N10)
A11: 44943 | B11: AMZU | C11: AMZN | D11: 96.050003 | E11: 13.590579 | F11: 26092 | G11: -91789 | H11: =D11*F11 | I11: =E11*G11 | J11: =H11-I11 | K11: -0.0025 | L11: -54010.432 | M11: 39702.671 | N11: =-I11*K11/252 | O11: 0 | P11: =SUM($N$2:N11)
A12: 44944 | B12: AMZU | C12: AMZN | D12: 95.459999 | E12: 13.452164 | F12: 26092 | G12: -91789 | H12: =D12*F12 | I12: =E12*G12 | J12: =H12-I12 | K12: -0.0025 | L12: -15394.384 | M12: 12705.005 | N12: =-I12*K12/252 | O12: 0 | P12: =SUM($N$2:N12)
A13: 44945 | B13: AMZU | C13: AMZN | D13: 93.68 | E13: 13.066335 | F13: 26092 | G13: -91789 | H13: =D13*F13 | I13: =E13*G13 | J13: =H13-I13 | K13: -0.0025 | L13: -46443.728 | M13: 35414.855 | N13: =-I13*K13/252 | O13: 0 | P13: =SUM($N$2:N13)
... A21: 44957 | B21: AMZU | C21: AMZN | D21: 103.13 | E21: 15.035277 | F21: 26570 | G21: -92003 | H21: =D21*F21 | I21: =E21*G21 | J21: =H21-I21 | K21: -0.0025 | L21: 68550.446 | M21: -50142.081 | N21: =-I21*K21/252 | O21: 0 | P21: =SUM($N$2:N21)

Sheet ARKK_TARK
A1: date | B1: etf | C1: under | D1: ARKK Price | E1: TARK Price | F1: long_sh | G1: short_sh | H1: long_notional_usd | I1: short_notional_usd | J1: gross_notional_usd | K1: borrow_rate_annual | L1: daily_long_pnl_usd | M1: daily_short_pnl_usd | N1: daily_borrow_cost_usd | O1: is_rebal | P1: cum_borrow_cost_usd
A2: 44929 | B2: TARK | C2: ARKK | D2: 30.208069 | E2: 15.614188 | F2: 20537 | G2: -20077 | H2: =D2*F2 | I2: =E2*G2 | J2: =H2-I2 | K2: -0.02 | L2: 0 | M2: 0 | N2: =-I2*K2/252 | O2: 1 | P2: =SUM($N$2:N2)
A3: 44930 | B3: TARK | C3: ARKK | D3: 31.517153 | E3: 16.972794 | F3: 20537 | G3: -20077 | H3: =D3*F3 | I3: =E3*G3 | J3: =H3-I3 | K3: -0.02 | L3: 0 | M3: 0 | N3: =-I3*K3/252 | O3: 0 | P3: =SUM($N$2:N3)
A4: 44931 | B4: TARK | C4: ARKK | D4: 30.763439 | E4: 16.0527 | F4: 20537 | G4: -20077 | H4: =D4*F4 | I4: =E4*G4 | J4: =H4-I4 | K4: -0.02 | L4: -15479.016 | M4: 18472.718 | N4: =-I4*K4/252 | O4: 0 | P4: =SUM($N$2:N4)
A5: 44932 | B5: TARK | C5: ARKK | D5: 31.110544 | E5: 16.420738 | F5: 20537 | G5: -20077 | H5: =D5*F5 | I5: =E5*G5 | J5: =H5-I5 | K5: -0.02 | L5: 7128.4959 | M5: -7389.1025 | N5: =-I5*K5/252 | O5: 1 | P5: =SUM($N$2:N5)
A6: 44935 | B6: TARK | C6: ARKK | D6: 32.538635 | E6: 17.939871 | F6: 20537 | G6: -20077 | H6: =D6*F6 | I6: =E6*G6 | J6: =H6-I6 | K6: -0.02 | L6: 29328.706 | M6: -30499.625 | N6: =-I6*K6/252 | O6: 0 | P6: =SUM($N$2:N6)
A7: 44936 | B7: TARK | C7: ARKK | D7: 33.341934 | E7: 18.722931 | F7: 20537 | G7: -20077 | H7: =D7*F7 | I7: =E7*G7 | J7: =H7-I7 | K7: -0.02 | L7: 16497.351 | M7: -15721.497 | N7: =-I7*K7/252 | O7: 0 | P7: =SUM($N$2:N7)
A8: 44937 | B8: TARK | C8: ARKK | D8: 34.472504 | E8: 20.124605 | F8: 20537 | G8: -20077 | H8: =D8*F8 | I8: =E8*G8 | J8: =H8-I8 | K8: -0.02 | L8: 23218.505 | M8: -28141.414 | N8: =-I8*K8/252 | O8: 0 | P8: =SUM($N$2:N8)
A9: 44938 | B9: TARK | C9: ARKK | D9: 35.196468 | E9: 20.958563 | F9: 20537 | G9: -20077 | H9: =D9*F9 | I9: =E9*G9 | J9: =H9-I9 | K9: -0.02 | L9: 14868.063 | M9: -16743.368 | N9: =-I9*K9/252 | O9: 0 | P9: =SUM($N$2:N9)
A10: 44939 | B10: TARK | C10: ARKK | D10: 35.692333 | E10: 21.46755 | F10: 20537 | G10: -20077 | H10: =D10*F10 | I10: =E10*G10 | J10: =H10-I10 | K10: -0.02 | L10: 10183.577 | M10: -10218.941 | N10: =-I10*K10/252 | O10: 1 | P10: =SUM($N$2:N10)
A11: 44943 | B11: TARK | C11: ARKK | D11: 36.733646 | E11: 22.787004 | F11: 18788 | G11: -15784 | H11: =D11*F11 | I11: =E11*G11 | J11: =H11-I11 | K11: -0.02 | L11: 19564.192 | M11: -20826.265 | N11: =-I11*K11/252 | O11: 0 | P11: =SUM($N$2:N11)
A12: 44944 | B12: TARK | C12: ARKK | D12: 35.652664 | E12: 21.483212 | F12: 18788 | G12: -15784 | H12: =D12*F12 | I12: =E12*G12 | J12: =H12-I12 | K12: -0.02 | L12: -20309.494 | M12: 20579.068 | N12: =-I12*K12/252 | O12: 0 | P12: =SUM($N$2:N12)
A13: 44945 | B13: TARK | C13: ARKK | D13: 34.502258 | E13: 20.026722 | F13: 18788 | G13: -15784 | H13: =D13*F13 | I13: =E13*G13 | J13: =H13-I13 | K13: -0.02 | L13: -21613.826 | M13: 22989.231 | N13: =-I13*K13/252 | O13: 0 | P13: =SUM($N$2:N13)
... A21: 44957 | B21: TARK | C21: ARKK | D21: 39.599747 | E21: 26.048443 | F21: 17763 | G21: -13435 | H21: =D21*F21 | I21: =E21*G21 | J21: =H21-I21 | K21: -0.02 | L21: 25014.929 | M21: -24985.931 | N21: =-I21*K21/252 | O21: 0 | P21: =SUM($N$2:N21)

Sheet ASHR_CHAU
A1: date | B1: etf | C1: under | D1: ASHR Price | E1: CHAU Price | F1: long_sh | G1: short_sh | H1: long_notional_usd | I1: short_notional_usd | J1: gross_notional_usd | K1: borrow_rate_annual | L1: daily_long_pnl_usd | M1: daily_short_pnl_usd | N1: daily_borrow_cost_usd | O1: is_rebal | P1: cum_borrow_cost_usd
A2: 44929 | B2: CHAU | C2: ASHR | D2: 26.669592 | E2: 18.896013 | F2: 5713 | G2: -4099 | H2: =D2*F2 | I2: =E2*G2 | J2: =H2-I2 | K2: -0.01 | L2: 0 | M2: 0 | N2: =-I2*K2/252 | O2: 1 | P2: =SUM($N$2:N2)
A3: 44930 | B3: CHAU | C3: ASHR | D3: 27.140787 | E3: 19.546656 | F3: 5713 | G3: -4099 | H3: =D3*F3 | I3: =E3*G3 | J3: =H3-I3 | K3: -0.01 | L3: 0 | M3: 0 | N3: =-I3*K3/252 | O3: 0 | P3: =SUM($N$2:N3)
A4: 44931 | B4: CHAU | C4: ASHR | D4: 27.470623 | E4: 20.087328 | F4: 5713 | G4: -4099 | H4: =D4*F4 | I4: =E4*G4 | J4: =H4-I4 | K4: -0.01 | L4: 1884.3524 | M4: -2216.2158 | N4: =-I4*K4/252 | O4: 0 | P4: =SUM($N$2:N4)
A5: 44932 | B5: CHAU | C5: ASHR | D5: 28.007786 | E5: 20.866264 | F5: 5713 | G5: -4099 | H5: =D5*F5 | I5: =E5*G5 | J5: =H5-I5 | K5: -0.01 | L5: 3068.811 | M5: -3192.8602 | N5: =-I5*K5/252 | O5: 1 | P5: =SUM($N$2:N5)
A6: 44935 | B6: CHAU | C6: ASHR | D6: 28.215111 | E6: 21.122849 | F6: 5713 | G6: -3898 | H6: =D6*F6 | I6: =E6*G6 | J6: =H6-I6 | K6: -0.01 | L6: 1184.4476 | M6: -1000.1651 | N6: =-I6*K6/252 | O6: 0 | P6: =SUM($N$2:N6)
A7: 44936 | B7: CHAU | C7: ASHR | D7: 28.290503 | E7: 21.278637 | F7: 5713 | G7: -3898 | H7: =D7*F7 | I7: =E7*G7 | J7: =H7-I7 | K7: -0.01 | L7: 430.71318 | M7: -607.26327 | N7: =-I7*K7/252 | O7: 0 | P7: =SUM($N$2:N7)
A8: 44937 | B8: CHAU | C8: ASHR | D8: 28.365894 | E8: 21.397768 | F8: 5713 | G8: -3898 | H8: =D8*F8 | I8: =E8*G8 | J8: =H8-I8 | K8: -0.01 | L8: 430.71318 | M8: -464.37298 | N8: =-I8*K8/252 | O8: 0 | P8: =SUM($N$2:N8)
A9: 44938 | B9: CHAU | C9: ASHR | D9: 28.639187 | E9: 21.773493 | F9: 5713 | G9: -3898 | H9: =D9*F9 | I9: =E9*G9 | J9: =H9-I9 | K9: -0.01 | L9: 1561.3203 | M9: -1464.5752 | N9: =-I9*K9/252 | O9: 0 | P9: =SUM($N$2:N9)
A10: 44939 | B10: CHAU | C10: ASHR | D10: 29.072685 | E10: 22.387472 | F10: 5713 | G10: -3898 | H10: =D10*F10 | I10: =E10*G10 | J10: =H10-I10 | K10: -0.01 | L10: 2476.5763 | M10: -2393.2915 | N10: =-I10*K10/252 | O10: 1 | P10: =SUM($N$2:N10)
A11: 44943 | B11: CHAU | C11: ASHR | D11: 29.195194 | E11: 22.653223 | F11: 5665 | G11: -3740 | H11: =D11*F11 | I11: =E11*G11 | J11: =H11-I11 | K11: -0.01 | L11: 694.0135 | M11: -993.90831 | N11: =-I11*K11/252 | O11: 0 | P11: =SUM($N$2:N11)
A12: 44944 | B12: CHAU | C12: ASHR | D12: 28.997295 | E12: 22.385643 | F12: 5665 | G12: -3740 | H12: =D12*F12 | I12: =E12*G12 | J12: =H12-I12 | K12: -0.01 | L12: -1121.0971 | M12: 1000.7493 | N12: =-I12*K12/252 | O12: 0 | P12: =SUM($N$2:N12)
A13: 44945 | B13: CHAU | C13: ASHR | D13: 29.308281 | E13: 22.754032 | F13: 5665 | G13: -3740 | H13: =D13*F13 | I13: =E13*G13 | J13: =H13-I13 | K13: -0.01 | L13: 1761.7332 | M13: -1377.7753 | N13: =-I13*K13/252 | O13: 0 | P13: =SUM($N$2:N13)
... A21: 44957 | B21: CHAU | C21: ASHR | D21: 29.411943 | E21: 22.928144 | F21: 5793 | G21: -3678 | H21: =D21*F21 | I21: =E21*G21 | J21: =H21-I21 | K21: -0.01 | L21: -928.07244 | M21: 1028.0045 | N21: =-I21*K21/252 | O21: 0 | P21: =SUM($N$2:N21)

Sheet BABA_BABX
A1: date | B1: etf | C1: under | D1: BABA Price | E1: BABX Price | F1: long_sh | G1: short_sh | H1: long_notional_usd | I1: short_notional_usd | J1: gross_notional_usd | K1: borrow_rate_annual | L1: daily_long_pnl_usd | M1: daily_short_pnl_usd | N1: daily_borrow_cost_usd | O1: is_rebal | P1: cum_borrow_cost_usd
A2: 44929 | B2: BABX | C2: BABA | D2: 87.352951 | E2: 26.02 | F2: 5330 | G2: -8920 | H2: =D2*F2 | I2: =E2*G2 | J2: =H2-I2 | K2: -0.0275 | L2: 0 | M2: 0 | N2: =-I2*K2/252 | O2: 1 | P2: =SUM($N$2:N2)
A3: 44930 | B3: BABX | C3: BABA | D3: 98.692299 | E3: 31.917999 | F3: 5330 | G3: -8920 | H3: =D3*F3 | I3: =E3*G3 | J3: =H3-I3 | K3: -0.0275 | L3: 0 | M3: 0 | N3: =-I3*K3/252 | O3: 0 | P3: =SUM($N$2:N3)
A4: 44931 | B4: BABX | C4: BABA | D4: 99.319107 | E4: 32.348999 | F4: 5330 | G4: -8920 | H4: =D4*F4 | I4: =E4*G4 | J4: =H4-I4 | K4: -0.0275 | L4: 3340.8875 | M4: -3844.5178 | N4: =-I4*K4/252 | O4: 0 | P4: =SUM($N$2:N4)
A5: 44932 | B5: BABX | C5: BABA | D5: 101.99725 | E5: 33.73 | F5: 5330 | G5: -8920 | H5: =D5*F5 | I5: =E5*G5 | J5: =H5-I5 | K5: -0.0275 | L5: 14274.479 | M5: -12318.525 | N5: =-I5*K5/252 | O5: 1 | P5: =SUM($N$2:N5)
A6: 44935 | B6: BABX | C6: BABA | D6: 105.2547 | E6: 35.608002 | F6: 5330 | G6: -8035 | H6: =D6*F6 | I6: =E6*G6 | J6: =H6-I6 | K6: -0.0275 | L6: 17362.229 | M6: -15089.747 | N6: =-I6*K6/252 | O6: 0 | P6: =SUM($N$2:N6)
A7: 44936 | B7: BABX | C7: BABA | D7: 109.10096 | E7: 37.849998 | F7: 5330 | G7: -8035 | H7: =D7*F7 | I7: =E7*G7 | J7: =H7-I7 | K7: -0.0275 | L7: 20500.566 | M7: -18014.444 | N7: =-I7*K7/252 | O7: 0 | P7: =SUM($N$2:N7)
A8: 44937 | B8: BABX | C8: BABA | D8: 109.23392 | E8: 37.948002 | F8: 5330 | G8: -8035 | H8: =D8*F8 | I8: =E8*G8 | J8: =H8-I8 | K8: -0.0275 | L8: 708.66325 | M8: -787.45722 | N8: =-I8*K8/252 | O8: 0 | P8: =SUM($N$2:N8)
A9: 44938 | B9: BABX | C9: BABA | D9: 107.458 | E9: 36.860001 | F9: 5330 | G9: -8035 | H9: =D9*F9 | I9: =E9*G9 | J9: =H9-I9 | K9: -0.0275 | L9: -9465.6379 | M9: 8742.0901 | N9: =-I9*K9/252 | O9: 0 | P9: =SUM($N$2:N9)
A10: 44939 | B10: BABX | C10: BABA | D10: 111.12382 | E10: 39.012001 | F10: 5330 | G10: -8035 | H10: =D10*F10 | I10: =E10*G10 | J10: =H10-I10 | K10: -0.0275 | L10: 19538.806 | M10: -17291.323 | N10: =-I10*K10/252 | O10: 1 | P10: =SUM($N$2:N10)
A11: 44943 | B11: BABX | C11: BABA | D11: 109.39537 | E11: 37.958 | F11: 4529 | G11: -6431 | H11: =D11*F11 | I11: =E11*G11 | J11: =H11-I11 | K11: -0.0275 | L11: -7828.1363 | M11: 6778.2795 | N11: =-I11*K11/252 | O11: 0 | P11: =SUM($N$2:N11)
A12: 44944 | B12: BABX | C12: BABA | D12: 107.52447 | E12: 36.709999 | F12: 4529 | G12: -6431 | H12: =D12*F12 | I12: =E12*G12 | J12: =H12-I12 | K12: -0.0275 | L12: -8473.3198 | M12: 8025.8951 | N12: =-I12*K12/252 | O12: 0 | P12: =SUM($N$2:N12)
A13: 44945 | B13: BABX | C13: BABA | D13: 110.71545 | E13: 38.759998 | F13: 4529 | G13: -6431 | H13: =D13*F13 | I13: =E13*G13 | J13: =H13-I13 | K13: -0.0275 | L13: 14451.944 | M13: -13183.545 | N13: =-I13*K13/252 | O13: 0 | P13: =SUM($N$2:N13)
... A21: 44957 | B21: BABX | C21: BABA | D21: 104.65639 | E21: 34.779999 | F21: 4750 | G21: -6734 | H21: =D21*F21 | I21: =E21*G21 | J21: =H21-I21 | K21: -0.0275 | L21: -4511.0359 | M21: 3939.4095 | N21: =-I21*K21/252 | O21: 0 | P21: =SUM($N$2:N21)

Sheet COIN_CONL
A1: date | B1: etf | C1: under | D1: COIN Price | E1: CONL Price | F1: long_sh | G1: short_sh | H1: long_notional_usd | I1: short_notional_usd | J1: gross_notional_usd | K1: borrow_rate_annual | L1: daily_long_pnl_usd | M1: daily_short_pnl_usd | N1: daily_borrow_cost_usd | O1: is_rebal | P1: cum_borrow_cost_usd
A2: 44929 | B2: CONL | C2: COIN | D2: 33.599998 | E2: 4.2295198 | F2: 98778 | G2: -394919 | H2: =D2*F2 | I2: =E2*G2 | J2: =H2-I2 | K2: 0.03 | L2: 0 | M2: 0 | N2: =-I2*K2/252 | O2: 1 | P2: =SUM($N$2:N2)
A3: 44930 | B3: CONL | C3: COIN | D3: 37.700001 | E3: 5.0474935 | F3: 98778 | G3: -394919 | H3: =D3*F3 | I3: =E3*G3 | J3: =H3-I3 | K3: 0.03 | L3: 0 | M3: 0 | N3: =-I3*K3/252 | O3: 0 | P3: =SUM($N$2:N3)
A4: 44931 | B4: CONL | C4: COIN | D4: 33.529999 | E4: 4.1796441 | F4: 98778 | G4: -394919 | H4: =D4*F4 | I4: =E4*G4 | J4: =H4-I4 | K4: 0.03 | L4: -411904.46 | M4: 342730.2 | N4: =-I4*K4/252 | O4: 0 | P4: =SUM($N$2:N4)
A5: 44932 | B5: CONL | C5: COIN | D5: 33.259998 | E5: 4.1058269 | F5: 98778 | G5: -394919 | H5: =D5*F5 | I5: =E5*G5 | J5: =H5-I5 | K5: 0.03 | L5: -26670.105 | M5: 29151.836 | N5: =-I5*K5/252 | O5: 1 | P5: =SUM($N$2:N5)
A6: 44935 | B6: CONL | C6: COIN | D6: 38.27 | E6: 5.0574689 | F6: 98778 | G6: -394919 | H6: =D6*F6 | I6: =E6*G6 | J6: =H6-I6 | K6: 0.03 | L6: 494877.99 | M6: -375821.52 | N6: =-I6*K6/252 | O6: 0 | P6: =SUM($N$2:N6)
A7: 44936 | B7: CONL | C7: COIN | D7: 43.23 | E7: 6.0150962 | F7: 98778 | G7: -394919 | H7: =D7*F7 | I7: =E7*G7 | J7: =H7-I7 | K7: 0.03 | L7: 489938.79 | M7: -378185.21 | N7: =-I7*K7/252 | O7: 0 | P7: =SUM($N$2:N7)
A8: 44937 | B8: CONL | C8: COIN | D8: 43.790001 | E8: 6.1048737 | F8: 98778 | G8: -394919 | H8: =D8*F8 | I8: =E8*G8 | J8: =H8-I8 | K8: 0.03 | L8: 55315.816 | M8: -35454.829 | N8: =-I8*K8/252 | O8: 0 | P8: =SUM($N$2:N8)
A9: 44938 | B9: CONL | C9: COIN | D9: 47.549999 | E9: 6.9328222 | F9: 98778 | G9: -394919 | H9: =D9*F9 | I9: =E9*G9 | J9: =H9-I9 | K9: 0.03 | L9: 371405.11 | M9: -326972.62 | N9: =-I9*K9/252 | O9: 0 | P9: =SUM($N$2:N9)
A10: 44939 | B10: CONL | C10: COIN | D10: 49.98 | E10: 7.4315863 | F10: 98778 | G10: -394919 | H10: =D10*F10 | I10: =E10*G10 | J10: =H10-I10 | K10: 0.03 | L10: 240030.57 | M10: -196971.4 | N10: =-I10*K10/252 | O10: 1 | P10: =SUM($N$2:N10)
A11: 44943 | B11: CONL | C11: COIN | D11: 54.139999 | E11: 8.3493128 | F11: 71778 | G11: -242944 | H11: =D11*F11 | I11: =E11*G11 | J11: =H11-I11 | K11: 0.03 | L11: 298596.47 | M11: -222956.15 | N11: =-I11*K11/252 | O11: 0 | P11: =SUM($N$2:N11)
A12: 44944 | B12: CONL | C12: COIN | D12: 50.209999 | E12: 7.4216113 | F12: 71778 | G12: -242944 | H12: =D12*F12 | I12: =E12*G12 | J12: =H12-I12 | K12: 0.03 | L12: -282087.56 | M12: 225379.51 | N12: =-I12*K12/252 | O12: 0 | P12: =SUM($N$2:N12)
A13: 44945 | B13: CONL | C13: COIN | D13: 49.419998 | E13: 7.2819571 | F13: 71778 | G13: -242944 | H13: =D13*F13 | I13: =E13*G13 | J13: =H13-I13 | K13: 0.03 | L13: -56704.686 | M13: 33928.14 | N13: =-I13*K13/252 | O13: 0 | P13: =SUM($N$2:N13)
... A21: 44957 | B21: CONL | C21: COIN | D21: 58.48 | E21: 9.167285 | F21: 62026 | G21: -193596 | H21: =D21*F21 | I21: =E21*G21 | J21: =H21-I21 | K21: 0.03 | L21: 143900.3 | M21: -98489.742 | N21: =-I21*K21/252 | O21: 0 | P21: =SUM($N$2:N21)

Sheet EWW_MEXX
A1: date | B1: etf | C1: under | D1: EWW Price | E1: MEXX Price | F1: long_sh | G1: short_sh | H1: long_notional_usd | I1: short_notional_usd | J1: gross_notional_usd | K1: borrow_rate_annual | L1: daily_long_pnl_usd | M1: daily_short_pnl_usd | N1: daily_borrow_cost_usd | O1: is_rebal | P1: cum_borrow_cost_usd
A2: 44929 | B2: MEXX | C2: EWW | D2: 45.605125 | E2: 16.087936 | F2: 9067 | G2: -8695 | H2: =D2*F2 | I2: =E2*G2 | J2: =H2-I2 | K2: 0.0075 | L2: 0 | M2: 0 | N2: =-I2*K2/252 | O2: 1 | P2: =SUM($N$2:N2)
A3: 44930 | B3: MEXX | C3: EWW | D3: 46.710384 | E3: 17.266186 | F3: 9067 | G3: -8695 | H3: =D3*F3 | I3: =E3*G3 | J3: =H3-I3 | K3: 0.0075 | L3: 0 | M3: 0 | N3: =-I3*K3/252 | O3: 0 | P3: =SUM($N$2:N3)
A4: 44931 | B4: MEXX | C4: EWW | D4: 47.317356 | E4: 17.931959 | F4: 9067 | G4: -8695 | H4: =D4*F4 | I4: =E4*G4 | J4: =H4-I4 | K4: 0.0075 | L4: 5503.4128 | M4: -5788.8996 | N4: =-I4*K4/252 | O4: 0 | P4: =SUM($N$2:N4)
A5: 44932 | B5: MEXX | C5: EWW | D5: 48.649094 | E5: 19.488749 | F5: 9067 | G5: -8695 | H5: =D5*F5 | I5: =E5*G5 | J5: =H5-I5 | K5: 0.0075 | L5: 12074.864 | M5: -13536.284 | N5: =-I5*K5/252 | O5: 1 | P5: =SUM($N$2:N5)
A6: 44935 | B6: MEXX | C6: EWW | D6: 49.05677 | E6: 19.988855 | F6: 9067 | G6: -7657 | H6: =D6*F6 | I6: =E6*G6 | J6: =H6-I6 | K6: 0.0075 | L6: 3696.4046 | M6: -3829.3179 | N6: =-I6*K6/252 | O6: 0 | P6: =SUM($N$2:N6)
A7: 44936 | B7: MEXX | C7: EWW | D7: 49.364788 | E7: 20.358553 | F7: 9067 | G7: -7657 | H7: =D7*F7 | I7: =E7*G7 | J7: =H7-I7 | K7: 0.0075 | L7: 2792.7968 | M7: -2830.7743 | N7: =-I7*K7/252 | O7: 0 | P7: =SUM($N$2:N7)
A8: 44937 | B8: MEXX | C8: EWW | D8: 50.45192 | E8: 21.491413 | F8: 9067 | G8: -7657 | H8: =D8*F8 | I8: =E8*G8 | J8: =H8-I8 | K8: 0.0075 | L8: 9857.0213 | M8: -8674.3104 | N8: =-I8*K8/252 | O8: 0 | P8: =SUM($N$2:N8)
A9: 44938 | B9: MEXX | C9: EWW | D9: 51.176674 | E9: 22.519499 | F9: 9067 | G9: -7657 | H9: =D9*F9 | I9: =E9*G9 | J9: =H9-I9 | K9: 0.0075 | L9: 6571.3475 | M9: -7872.0523 | N9: =-I9*K9/252 | O9: 0 | P9: =SUM($N$2:N9)
A10: 44939 | B10: MEXX | C10: EWW | D10: 51.348804 | E10: 22.892878 | F10: 9067 | G10: -7657 | H10: =D10*F10 | I10: =E10*G10 | J10: =H10-I10 | K10: 0.0075 | L10: 1560.708 | M10: -2858.9611 | N10: =-I10*K10/252 | O10: 1 | P10: =SUM($N$2:N10)
A11: 44943 | B11: MEXX | C11: EWW | D11: 51.23103 | E11: 22.661545 | F11: 8705 | G11: -6605 | H11: =D11*F11 | I11: =E11*G11 | J11: =H11-I11 | K11: 0.0075 | L11: -1025.2311 | M11: 1527.953 | N11: =-I11*K11/252 | O11: 0 | P11: =SUM($N$2:N11)
A12: 44944 | B12: MEXX | C12: EWW | D12: 50.778061 | E12: 22.048531 | F12: 8705 | G12: -6605 | H12: =D12*F12 | I12: =E12*G12 | J12: =H12-I12 | K12: 0.0075 | L12: -3943.0916 | M12: 4048.9589 | N12: =-I12*K12/252 | O12: 0 | P12: =SUM($N$2:N12)
A13: 44945 | B13: MEXX | C13: EWW | D13: 50.741817 | E13: 21.985254 | F13: 8705 | G13: -6605 | H13: =D13*F13 | I13: =E13*G13 | J13: =H13-I13 | K13: 0.0075 | L13: -315.49913 | M13: 417.9399 | N13: =-I13*K13/252 | O13: 0 | P13: =SUM($N$2:N13)
... A21: 44957 | B21: MEXX | C21: EWW | D21: 52.22757 | E21: 23.841082 | F21: 9018 | G21: -6603 | H21: =D21*F21 | I21: =E21*G21 | J21: =H21-I21 | K21: 0.0075 | L21: 245.1411 | M21: 239.95773 | N21: =-I21*K21/252 | O21: 0 | P21: =SUM($N$2:N21)

Sheet EWY_KORU
A1: date | B1: etf | C1: under | D1: EWY Price | E1: KORU Price | F1: long_sh | G1: short_sh | H1: long_notional_usd | I1: short_notional_usd | J1: gross_notional_usd | K1: borrow_rate_annual | L1: daily_long_pnl_usd | M1: daily_short_pnl_usd | N1: daily_borrow_cost_usd | O1: is_rebal | P1: cum_borrow_cost_usd
A2: 44929 | B2: KORU | C2: EWY | D2: 51.599609 | E2: 66.1492 | F2: 12826 | G2: -3410 | H2: =D2*F2 | I2: =E2*G2 | J2: =H2-I2 | K2: 0.0225 | L2: 0 | M2: 0 | N2: =-I2*K2/252 | O2: 1 | P2: =SUM($N$2:N2)
A3: 44930 | B3: KORU | C3: EWY | D3: 53.638271 | E3: 73.717125 | F3: 12826 | G3: -3410 | H3: =D3*F3 | I3: =E3*G3 | J3: =H3-I3 | K3: 0.0225 | L3: 0 | M3: 0 | N3: =-I3*K3/252 | O3: 0 | P3: =SUM($N$2:N3)
A4: 44931 | B4: KORU | C4: EWY | D4: 53.070423 | E4: 71.47477 | F4: 12826 | G4: -3410 | H4: =D4*F4 | I4: =E4*G4 | J4: =H4-I4 | K4: 0.0225 | L4: -7283.2211 | M4: 7646.4317 | N4: =-I4*K4/252 | O4: 0 | P4: =SUM($N$2:N4)
A5: 44932 | B5: KORU | C5: EWY | D5: 55.751411 | E5: 82.593063 | F5: 12826 | G5: -3410 | H5: =D5*F5 | I5: =E5*G5 | J5: =H5-I5 | K5: 0.0225 | L5: 34386.356 | M5: -37913.382 | N5: =-I5*K5/252 | O5: 1 | P5: =SUM($N$2:N5)
A6: 44935 | B6: KORU | C6: EWY | D6: 56.924339 | E6: 87.731789 | F6: 12826 | G6: -2951 | H6: =D6*F6 | I6: =E6*G6 | J6: =H6-I6 | K6: 0.0225 | L6: 15043.973 | M6: -15164.378 | N6: =-I6*K6/252 | O6: 0 | P6: =SUM($N$2:N6)
A7: 44936 | B7: KORU | C7: EWY | D7: 57.110516 | E7: 88.572655 | F7: 12826 | G7: -2951 | H7: =D7*F7 | I7: =E7*G7 | J7: =H7-I7 | K7: 0.0225 | L7: 2387.8972 | M7: -2481.3958 | N7: =-I7*K7/252 | O7: 0 | P7: =SUM($N$2:N7)
A8: 44937 | B8: KORU | C8: EWY | D8: 57.259464 | E8: 89.226662 | F8: 12826 | G8: -2951 | H8: =D8*F8 | I8: =E8*G8 | J8: =H8-I8 | K8: 0.0225 | L8: 1910.4156 | M8: -1929.9745 | N8: =-I8*K8/252 | O8: 0 | P8: =SUM($N$2:N8)
A9: 44938 | B9: KORU | C9: EWY | D9: 57.678364 | E9: 91.188744 | F9: 12826 | G9: -2951 | H9: =D9*F9 | I9: =E9*G9 | J9: =H9-I9 | K9: 0.0225 | L9: 5372.8055 | M9: -5790.1037 | N9: =-I9*K9/252 | O9: 0 | P9: =SUM($N$2:N9)
A10: 44939 | B10: KORU | C10: EWY | D10: 58.106575 | E10: 93.150787 | F10: 12826 | G10: -2951 | H10: =D10*F10 | I10: =E10*G10 | J10: =H10-I10 | K10: 0.0225 | L10: 5492.237 | M10: -5789.9911 | N10: =-I10*K10/252 | O10: 1 | P10: =SUM($N$2:N10)
A11: 44943 | B11: KORU | C11: EWY | D11: 57.948322 | E11: 92.309921 | F11: 12312 | G11: -2618 | H11: =D11*F11 | I11: =E11*G11 | J11: =H11-I11 | K11: 0.0225 | L11: -1948.4074 | M11: 2201.3874 | N11: =-I11*K11/252 | O11: 0 | P11: =SUM($N$2:N11)
A12: 44944 | B12: KORU | C12: EWY | D12: 57.082592 | E12: 88.292358 | F12: 12312 | G12: -2618 | H12: =D12*F12 | I12: =E12*G12 | J12: =H12-I12 | K12: 0.0225 | L12: -10658.871 | M12: 10517.98 | N12: =-I12*K12/252 | O12: 0 | P12: =SUM($N$2:N12)
A13: 44945 | B13: KORU | C13: EWY | D13: 57.873852 | E13: 91.562462 | F13: 12312 | G13: -2618 | H13: =D13*F13 | I13: =E13*G13 | J13: =H13-I13 | K13: 0.0225 | L13: 9741.9902 | M13: -8561.1308 | N13: =-I13*K13/252 | O13: 0 | P13: =SUM($N$2:N13)
... A21: 44957 | B21: KORU | C21: EWY | D21: 59.084019 | E21: 96.607735 | F21: 12466 | G21: -2427 | H21: =D21*F21 | I21: =E21*G21 | J21: =H21-I21 | K21: 0.0225 | L21: -5802.3508 | M21: 6575.9827 | N21: =-I21*K21/252 | O21: 0 | P21: =SUM($N$2:N21)

Sheet FXI_YINN
A1: date | B1: etf | C1: under | D1: FXI Price | E1: YINN Price | F1: long_sh | G1: short_sh | H1: long_notional_usd | I1: short_notional_usd | J1: gross_notional_usd | K1: borrow_rate_annual | L1: daily_long_pnl_usd | M1: daily_short_pnl_usd | N1: daily_borrow_cost_usd | O1: is_rebal | P1: cum_borrow_cost_usd
A2: 44929 | B2: YINN | C2: FXI | D2: 27.235073 | E2: 47.690964 | F2: 35048 | G2: -6728 | H2: =D2*F2 | I2: =E2*G2 | J2: =H2-I2 | K2: -0.02 | L2: 0 | M2: 0 | N2: =-I2*K2/252 | O2: 1 | P2: =SUM($N$2:N2)
A3: 44930 | B3: YINN | C3: FXI | D3: 28.972097 | E3: 56.750477 | F3: 35048 | G3: -6728 | H3: =D3*F3 | I3: =E3*G3 | J3: =H3-I3 | K3: -0.02 | L3: 0 | M3: 0 | N3: =-I3*K3/252 | O3: 0 | P3: =SUM($N$2:N3)
A4: 44931 | B4: YINN | C4: FXI | D4: 28.907076 | E4: 56.488686 | F4: 35048 | G4: -6728 | H4: =D4*F4 | I4: =E4*G4 | J4: =H4-I4 | K4: -0.02 | L4: -2278.8741 | M4: 1761.3314 | N4: =-I4*K4/252 | O4: 0 | P4: =SUM($N$2:N4)
A5: 44932 | B5: YINN | C5: FXI | D5: 28.981388 | E5: 56.956158 | F5: 35048 | G5: -6728 | H5: =D5*F5 | I5: =E5*G5 | J5: =H5-I5 | K5: -0.02 | L5: 2604.4943 | M5: -3145.1521 | N5: =-I5*K5/252 | O5: 1 | P5: =SUM($N$2:N5)
A6: 44935 | B6: YINN | C6: FXI | D6: 28.981388 | E6: 57.058998 | F6: 35048 | G6: -5995 | H6: =D6*F6 | I6: =E6*G6 | J6: =H6-I6 | K6: -0.02 | L6: 0 | M6: -616.52834 | N6: =-I6*K6/252 | O6: 0 | P6: =SUM($N$2:N6)
A7: 44936 | B7: YINN | C7: FXI | D7: 29.343655 | E7: 58.956909 | F7: 35048 | G7: -5995 | H7: =D7*F7 | I7: =E7*G7 | J7: =H7-I7 | K7: -0.02 | L7: 12696.718 | M7: -11377.977 | N7: =-I7*K7/252 | O7: 0 | P7: =SUM($N$2:N7)
A8: 44937 | B8: YINN | C8: FXI | D8: 29.6409 | E8: 60.723934 | F8: 35048 | G8: -5995 | H8: =D8*F8 | I8: =E8*G8 | J8: =H8-I8 | K8: -0.02 | L8: 10417.844 | M8: -10593.315 | N8: =-I8*K8/252 | O8: 0 | P8: =SUM($N$2:N8)
A9: 44938 | B9: YINN | C9: FXI | D9: 29.3901 | E9: 59.125214 | F9: 35048 | G9: -5995 | H9: =D9*F9 | I9: =E9*G9 | J9: =H9-I9 | K9: -0.02 | L9: -8790.0096 | M9: 9584.3297 | N9: =-I9*K9/252 | O9: 0 | P9: =SUM($N$2:N9)
A10: 44939 | B10: YINN | C10: FXI | D10: 29.808098 | E10: 61.593426 | F10: 35048 | G10: -5995 | H10: =D10*F10 | I10: =E10*G10 | J10: =H10-I10 | K10: -0.02 | L10: 14649.971 | M10: -14796.932 | N10: =-I10*K10/252 | O10: 1 | P10: =SUM($N$2:N10)
A11: 44943 | B11: YINN | C11: FXI | D11: 29.157875 | E11: 57.638653 | F11: 34614 | G11: -5631 | H11: =D11*F11 | I11: =E11*G11 | J11: =H11-I11 | K11: -0.02 | L11: -22506.811 | M11: 22269.326 | N11: =-I11*K11/252 | O11: 0 | P11: =SUM($N$2:N11)
A12: 44944 | B12: YINN | C12: FXI | D12: 28.869919 | E12: 55.843582 | F12: 34614 | G12: -5631 | H12: =D12*F12 | I12: =E12*G12 | J12: =H12-I12 | K12: -0.02 | L12: -9967.3172 | M12: 10108.043 | N12: =-I12*K12/252 | O12: 0 | P12: =SUM($N$2:N12)
A13: 44945 | B13: YINN | C13: FXI | D13: 29.445833 | E13: 59.274788 | F13: 34614 | G13: -5631 | H13: =D13*F13 | I13: =E13*G13 | J13: =H13-I13 | K13: -0.02 | L13: 19934.7 | M13: -19321.12 | N13: =-I13*K13/252 | O13: 0 | P13: =SUM($N$2:N13)
... A21: 44957 | B21: YINN | C21: FXI | D21: 29.538721 | E21: 59.405682 | F21: 35468 | G21: -5418 | H21: =D21*F21 | I21: =E21*G21 | J21: =H21-I21 | K21: -0.02 | L21: -6589.2298 | M21: 5369.3888 | N21: =-I21*K21/252 | O21: 0 | P21: =SUM($N$2:N21)

Sheet GDXJ_JNUG
A1: date | B1: etf | C1: under | D1: GDXJ Price | E1: JNUG Price | F1: long_sh | G1: short_sh | H1: long_notional_usd | I1: short_notional_usd | J1: gross_notional_usd | K1: borrow_rate_annual | L1: daily_long_pnl_usd | M1: daily_short_pnl_usd | N1: daily_borrow_cost_usd | O1: is_rebal | P1: cum_borrow_cost_usd
A2: 44929 | B2: JNUG | C2: GDXJ | D2: 34.869011 | E2: 36.153866 | F2: 13873 | G2: -6778 | H2: =D2*F2 | I2: =E2*G2 | J2: =H2-I2 | K2: -0.005 | L2: 0 | M2: 0 | N2: =-I2*K2/252 | O2: 1 | P2: =SUM($N$2:N2)
A3: 44930 | B3: JNUG | C3: GDXJ | D3: 36.552864 | E3: 39.542702 | F3: 13873 | G3: -6778 | H3: =D3*F3 | I3: =E3*G3 | J3: =H3-I3 | K3: -0.005 | L3: 0 | M3: 0 | N3: =-I3*K3/252 | O3: 0 | P3: =SUM($N$2:N3)
A4: 44931 | B4: JNUG | C4: GDXJ | D4: 36.070415 | E4: 38.606567 | F4: 13873 | G4: -6778 | H4: =D4*F4 | I4: =E4*G4 | J4: =H4-I4 | K4: -0.005 | L4: -6693.0091 | M4: 6345.1185 | N4: =-I4*K4/252 | O4: 0 | P4: =SUM($N$2:N4)
A5: 44932 | B5: JNUG | C5: GDXJ | D5: 37.347492 | E5: 41.255856 | F5: 13873 | G5: -6778 | H5: =D5*F5 | I5: =E5*G5 | J5: =H5-I5 | K5: -0.005 | L5: 17716.885 | M5: -17956.875 | N5: =-I5*K5/252 | O5: 1 | P5: =SUM($N$2:N5)
A6: 44935 | B6: JNUG | C6: GDXJ | D6: 36.808281 | E6: 40.169926 | F6: 13873 | G6: -6362 | H6: =D6*F6 | I6: =E6*G6 | J6: =H6-I6 | K6: -0.005 | L6: -7480.478 | M6: 6908.6858 | N6: =-I6*K6/252 | O6: 0 | P6: =SUM($N$2:N6)
A7: 44936 | B7: JNUG | C7: GDXJ | D7: 37.53669 | E7: 41.639671 | F7: 13873 | G7: -6362 | H7: =D7*F7 | I7: =E7*G7 | J7: =H7-I7 | K7: -0.005 | L7: 10105.215 | M7: -9350.5217 | N7: =-I7*K7/252 | O7: 0 | P7: =SUM($N$2:N7)
A8: 44937 | B8: JNUG | C8: GDXJ | D8: 36.988014 | E8: 40.553738 | F8: 13873 | G8: -6362 | H8: =D8*F8 | I8: =E8*G8 | J8: =H8-I8 | K8: -0.005 | L8: -7611.7757 | M8: 6908.7101 | N8: =-I8*K8/252 | O8: 0 | P8: =SUM($N$2:N8)
A9: 44938 | B9: JNUG | C9: GDXJ | D9: 37.744804 | E9: 41.995407 | F9: 13873 | G9: -6362 | H9: =D9*F9 | I9: =E9*G9 | J9: =H9-I9 | K9: -0.005 | L9: 10498.95 | M9: -9171.9011 | N9: =-I9*K9/252 | O9: 0 | P9: =SUM($N$2:N9)
A10: 44939 | B10: JNUG | C10: GDXJ | D10: 38.2178 | E10: 43.081326 | F10: 13873 | G10: -6362 | H10: =D10*F10 | I10: =E10*G10 | J10: =H10-I10 | K10: -0.005 | L10: 6561.8702 | M10: -6908.613 | N10: =-I10*K10/252 | O10: 1 | P10: =SUM($N$2:N10)
A11: 44943 | B11: JNUG | C11: GDXJ | D11: 36.988014 | E11: 40.450764 | F11: 13681 | G11: -6148 | H11: =D11*F11 | I11: =E11*G11 | J11: =H11-I11 | K11: -0.005 | L11: -16824.701 | M11: 16172.694 | N11: =-I11*K11/252 | O11: 0 | P11: =SUM($N$2:N11)
A12: 44944 | B12: JNUG | C12: GDXJ | D12: 36.477188 | E12: 39.252495 | F12: 13681 | G12: -6148 | H12: =D12*F12 | I12: =E12*G12 | J12: =H12-I12 | K12: -0.005 | L12: -6988.612 | M12: 7366.9571 | N12: =-I12*K12/252 | O12: 0 | P12: =SUM($N$2:N12)
A13: 44945 | B13: JNUG | C13: GDXJ | D13: 37.46101 | E13: 41.312016 | F13: 13681 | G13: -6148 | H13: =D13*F13 | I13: =E13*G13 | J13: =H13-I13 | K13: -0.005 | L13: 13459.667 | M13: -12661.933 | N13: =-I13*K13/252 | O13: 0 | P13: =SUM($N$2:N13)
... A21: 44957 | B21: JNUG | C21: GDXJ | D21: 36.846123 | E21: 39.786106 | F21: 14851 | G21: -6847 | H21: =D21*F21 | I21: =E21*G21 | J21: =H21-I21 | K21: -0.005 | L21: 2388.3946 | M21: -1346.0285 | N21: =-I21*K21/252 | O21: 0 | P21: =SUM($N$2:N21)

Sheet GDX_GDXU
A1: date | B1: etf | C1: under | D1: GDX Price | E1: GDXU Price | F1: long_sh | G1: short_sh | H1: long_notional_usd | I1: short_notional_usd | J1: gross_notional_usd | K1: borrow_rate_annual | L1: daily_long_pnl_usd | M1: daily_short_pnl_usd | N1: daily_borrow_cost_usd | O1: is_rebal | P1: cum_borrow_cost_usd
A2: 44929 | B2: GDXU | C2: GDX | D2: 28.63427 | E2: 46.52 | F2: 53192 | G2: -10760 | H2: =D2*F2 | I2: =E2*G2 | J2: =H2-I2 | K2: -0.005 | L2: 0 | M2: 0 | N2: =-I2*K2/252 | O2: 1 | P2: =SUM($N$2:N2)
A3: 44930 | B3: GDXU | C3: GDX | D3: 29.850693 | E3: 52.400002 | F3: 53192 | G3: -10760 | H3: =D3*F3 | I3: =E3*G3 | J3: =H3-I3 | K3: -0.005 | L3: 0 | M3: 0 | N3: =-I3*K3/252 | O3: 0 | P3: =SUM($N$2:N3)
A4: 44931 | B4: GDXU | C4: GDX | D4: 29.590031 | E4: 51.419998 | F4: 53192 | G4: -10760 | H4: =D4*F4 | I4: =E4*G4 | J4: =H4-I4 | K4: -0.005 | L4: -13865.137 | M4: 10544.836 | N4: =-I4*K4/252 | O4: 0 | P4: =SUM($N$2:N4)
A5: 44932 | B5: GDXU | C5: GDX | D5: 30.468563 | E5: 55.400002 | F5: 53192 | G5: -10760 | H5: =D5*F5 | I5: =E5*G5 | J5: =H5-I5 | K5: -0.005 | L5: 46730.896 | M5: -42824.836 | N5: =-I5*K5/252 | O5: 1 | P5: =SUM($N$2:N5)
A6: 44935 | B6: GDXU | C6: GDX | D6: 30.178938 | E6: 54.389999 | F6: 53192 | G6: -9614 | H6: =D6*F6 | I6: =E6*G6 | J6: =H6-I6 | K6: -0.005 | L6: -15405.742 | M6: 9710.1605 | N6: =-I6*K6/252 | O6: 0 | P6: =SUM($N$2:N6)
A7: 44936 | B7: GDXU | C7: GDX | D7: 30.738878 | E7: 57 | F7: 53192 | G7: -9614 | H7: =D7*F7 | I7: =E7*G7 | J7: =H7-I7 | K7: -0.005 | L7: 29784.346 | M7: -25092.546 | N7: =-I7*K7/252 | O7: 0 | P7: =SUM($N$2:N7)
A8: 44937 | B8: GDXU | C8: GDX | D8: 30.478216 | E8: 55.5 | F8: 53192 | G8: -9614 | H8: =D8*F8 | I8: =E8*G8 | J8: =H8-I8 | K8: -0.005 | L8: -13865.137 | M8: 14421 | N8: =-I8*K8/252 | O8: 0 | P8: =SUM($N$2:N8)
A9: 44938 | B9: GDXU | C9: GDX | D9: 31.067122 | E9: 58.459999 | F9: 53192 | G9: -9614 | H9: =D9*F9 | I9: =E9*G9 | J9: =H9-I9 | K9: -0.005 | L9: 31325.053 | M9: -28457.431 | N9: =-I9*K9/252 | O9: 0 | P9: =SUM($N$2:N9)
A10: 44939 | B10: GDXU | C10: GDX | D10: 31.52087 | E10: 60.900002 | F10: 53192 | G10: -9614 | H10: =D10*F10 | I10: =E10*G10 | J10: =H10-I10 | K10: -0.005 | L10: 24135.801 | M10: -23458.183 | N10: =-I10*K10/252 | O10: 1 | P10: =SUM($N$2:N10)
A11: 44943 | B11: GDXU | C11: GDX | D11: 30.429947 | E11: 54.669998 | F11: 52231 | G11: -8884 | H11: =D11*F11 | I11: =E11*G11 | J11: =H11-I11 | K11: -0.005 | L11: -56980.015 | M11: 55347.35 | N11: =-I11*K11/252 | O11: 0 | P11: =SUM($N$2:N11)
A12: 44944 | B12: GDXU | C12: GDX | D12: 30.130665 | E12: 52.889999 | F12: 52231 | G12: -8884 | H12: =D12*F12 | I12: =E12*G12 | J12: =H12-I12 | K12: -0.005 | L12: -15631.802 | M12: 15813.509 | N12: =-I12*K12/252 | O12: 0 | P12: =SUM($N$2:N12)
A13: 44945 | B13: GDXU | C13: GDX | D13: 30.912655 | E13: 56.889999 | F13: 52231 | G13: -8884 | H13: =D13*F13 | I13: =E13*G13 | J13: =H13-I13 | K13: -0.005 | L13: 40844.122 | M13: -35536 | N13: =-I13*K13/252 | O13: 0 | P13: =SUM($N$2:N13)
... A21: 44957 | B21: GDXU | C21: GDX | D21: 30.912655 | E21: 55.439999 | F21: 56004 | G21: -9980 | H21: =D21*F21 | I21: =E21*G21 | J21: =H21-I21 | K21: -0.005 | L21: 10272.798 | M21: -7884.1711 | N21: =-I21*K21/252 | O21: 0 | P21: =SUM($N$2:N21)

Sheet GDX_NUGT
A1: date | B1: etf | C1: under | D1: GDX Price | E1: NUGT Price | F1: long_sh | G1: short_sh | H1: long_notional_usd | I1: short_notional_usd | J1: gross_notional_usd | K1: borrow_rate_annual | L1: daily_long_pnl_usd | M1: daily_short_pnl_usd | N1: daily_borrow_cost_usd | O1: is_rebal | P1: cum_borrow_cost_usd
A2: 44929 | B2: NUGT | C2: GDX | D2: 28.63427 | E2: 35.285088 | F2: 15820 | G2: -6494 | H2: =D2*F2 | I2: =E2*G2 | J2: =H2-I2 | K2: -0.0175 | L2: 0 | M2: 0 | N2: =-I2*K2/252 | O2: 1 | P2: =SUM($N$2:N2)
A3: 44930 | B3: NUGT | C3: GDX | D3: 29.850693 | E3: 38.310349 | F3: 15820 | G3: -6494 | H3: =D3*F3 | I3: =E3*G3 | J3: =H3-I3 | K3: -0.0175 | L3: 0 | M3: 0 | N3: =-I3*K3/252 | O3: 0 | P3: =SUM($N$2:N3)
A4: 44931 | B4: NUGT | C4: GDX | D4: 29.590031 | E4: 37.83976 | F4: 15820 | G4: -6494 | H4: =D4*F4 | I4: =E4*G4 | J4: =H4-I4 | K4: -0.0175 | L4: -4123.6741 | M4: 3056.0029 | N4: =-I4*K4/252 | O4: 0 | P4: =SUM($N$2:N4)
A5: 44932 | B5: NUGT | C5: GDX | D5: 30.468563 | E5: 39.731743 | F5: 15820 | G5: -6494 | H5: =D5*F5 | I5: =E5*G5 | J5: =H5-I5 | K5: -0.0175 | L5: 13898.383 | M5: -12286.538 | N5: =-I5*K5/252 | O5: 1 | P5: =SUM($N$2:N5)
A6: 44935 | B6: NUGT | C6: GDX | D6: 30.178938 | E6: 39.241936 | F6: 15820 | G6: -6136 | H6: =D6*F6 | I6: =E6*G6 | J6: =H6-I6 | K6: -0.0175 | L6: -4581.8702 | M6: 3005.4565 | N6: =-I6*K6/252 | O6: 0 | P6: =SUM($N$2:N6)
A7: 44936 | B7: NUGT | C7: GDX | D7: 30.738878 | E7: 40.576897 | F7: 15820 | G7: -6136 | H7: =D7*F7 | I7: =E7*G7 | J7: =H7-I7 | K7: -0.0175 | L7: 8858.2561 | M7: -8191.3203 | N7: =-I7*K7/252 | O7: 0 | P7: =SUM($N$2:N7)
A8: 44937 | B8: NUGT | C8: GDX | D8: 30.478216 | E8: 39.933426 | F8: 15820 | G8: -6136 | H8: =D8*F8 | I8: =E8*G8 | J8: =H8-I8 | K8: -0.0175 | L8: -4123.6741 | M8: 3948.3366 | N8: =-I8*K8/252 | O8: 0 | P8: =SUM($N$2:N8)
A9: 44938 | B9: NUGT | C9: GDX | D9: 31.067122 | E9: 41.39323 | F9: 15820 | G9: -6136 | H9: =D9*F9 | I9: =E9*G9 | J9: =H9-I9 | K9: -0.0175 | L9: 9316.4824 | M9: -8957.3606 | N9: =-I9*K9/252 | O9: 0 | P9: =SUM($N$2:N9)
A10: 44939 | B10: NUGT | C10: GDX | D10: 31.52087 | E10: 42.574528 | F10: 15820 | G10: -6136 | H10: =D10*F10 | I10: =E10*G10 | J10: =H10-I10 | K10: -0.0175 | L10: 7178.3045 | M10: -7248.4402 | N10: =-I10*K10/252 | O10: 1 | P10: =SUM($N$2:N10)
A11: 44943 | B11: NUGT | C11: GDX | D11: 30.429947 | E11: 39.702927 | F11: 15534 | G11: -5817 | H11: =D11*F11 | I11: =E11*G11 | J11: =H11-I11 | K11: -0.0175 | L11: -16946.403 | M11: 16704.104 | N11: =-I11*K11/252 | O11: 0 | P11: =SUM($N$2:N11)
A12: 44944 | B12: NUGT | C12: GDX | D12: 30.130665 | E12: 38.934608 | F12: 15534 | G12: -5817 | H12: =D12*F12 | I12: =E12*G12 | J12: =H12-I12 | K12: -0.0175 | L12: -4649.0477 | M12: 4469.3068 | N12: =-I12*K12/252 | O12: 0 | P12: =SUM($N$2:N12)
A13: 44945 | B13: NUGT | C13: GDX | D13: 30.912655 | E13: 40.807388 | F13: 15534 | G13: -5817 | H13: =D13*F13 | I13: =E13*G13 | J13: =H13-I13 | K13: -0.0175 | L13: 12147.433 | M13: -10893.96 | N13: =-I13*K13/252 | O13: 0 | P13: =SUM($N$2:N13)
... A21: 44957 | B21: NUGT | C21: GDX | D21: 30.912655 | E21: 40.701748 | F21: 16656 | G21: -6322 | H21: =D21*F21 | I21: =E21*G21 | J21: =H21-I21 | K21: -0.0175 | L21: 3055.2054 | M21: -2793.0061 | N21: =-I21*K21/252 | O21: 0 | P21: =SUM($N$2:N21)

Sheet GOOGL_GGLL
A1: date | B1: etf | C1: under | D1: GOOGL Price | E1: GGLL Price | F1: long_sh | G1: short_sh | H1: long_notional_usd | I1: short_notional_usd | J1: gross_notional_usd | K1: borrow_rate_annual | L1: daily_long_pnl_usd | M1: daily_short_pnl_usd | N1: daily_borrow_cost_usd | O1: is_rebal | P1: cum_borrow_cost_usd
A2: 44929 | B2: GGLL | C2: GOOGL | D2: 88.389465 | E2: 16.232771 | F2: 20098 | G2: -54856 | H2: =D2*F2 | I2: =E2*G2 | J2: =H2-I2 | K2: 0 | L2: 0 | M2: 0 | N2: =-I2*K2/252 | O2: 1 | P2: =SUM($N$2:N2)
A3: 44930 | B3: GGLL | C3: GOOGL | D3: 87.357986 | E3: 15.949437 | F3: 20098 | G3: -54856 | H3: =D3*F3 | I3: =E3*G3 | J3: =H3-I3 | K3: 0 | L3: 0 | M3: 0 | N3: =-I3*K3/252 | O3: 0 | P3: =SUM($N$2:N3)
A4: 44931 | B4: GGLL | C4: GOOGL | D4: 85.493401 | E4: 15.458506 | F4: 20098 | G4: -54856 | H4: =D4*F4 | I4: =E4*G4 | J4: =H4-I4 | K4: 0 | L4: -37474.447 | M4: 26930.539 | N4: =-I4*K4/252 | O4: 0 | P4: =SUM($N$2:N4)
A5: 44932 | B5: GGLL | C5: GOOGL | D5: 86.624031 | E5: 15.725801 | F5: 20098 | G5: -54856 | H5: =D5*F5 | I5: =E5*G5 | J5: =H5-I5 | K5: 0 | L5: 22723.412 | M5: -14662.78 | N5: =-I5*K5/252 | O5: 1 | P5: =SUM($N$2:N5)
A6: 44935 | B6: GGLL | C6: GOOGL | D6: 87.298477 | E6: 15.939638 | F6: 20098 | G6: -54856 | H6: =D6*F6 | I6: =E6*G6 | J6: =H6-I6 | K6: 0 | L6: 13555.018 | M6: -11730.224 | N6: =-I6*K6/252 | O6: 0 | P6: =SUM($N$2:N6)
A7: 44936 | B7: GGLL | C7: GOOGL | D7: 87.69519 | E7: 15.993099 | F7: 20098 | G7: -54856 | H7: =D7*F7 | I7: =E7*G7 | J7: =H7-I7 | K7: 0 | L7: 7973.143 | M7: -2932.6607 | N7: =-I7*K7/252 | O7: 0 | P7: =SUM($N$2:N7)
A8: 44937 | B8: GGLL | C8: GOOGL | D8: 90.769775 | E8: 16.862694 | F8: 20098 | G8: -54856 | H8: =D8*F8 | I8: =E8*G8 | J8: =H8-I8 | K8: 0 | L8: 61793.009 | M8: -47702.48 | N8: =-I8*K8/252 | O8: 0 | P8: =SUM($N$2:N8)
A9: 44938 | B9: GGLL | C9: GOOGL | D9: 90.38298 | E9: 16.747761 | F9: 20098 | G9: -54856 | H9: =D9*F9 | I9: =E9*G9 | J9: =H9-I9 | K9: 0 | L9: -7773.8068 | M9: 6304.7654 | N9: =-I9*K9/252 | O9: 0 | P9: =SUM($N$2:N9)
A10: 44939 | B10: GGLL | C10: GOOGL | D10: 91.364868 | E10: 17.009705 | F10: 20098 | G10: -54856 | H10: =D10*F10 | I10: =E10*G10 | J10: =H10-I10 | K10: 0 | L10: 19733.981 | M10: -14369.19 | N10: =-I10*K10/252 | O10: 1 | P10: =SUM($N$2:N10)
A11: 44943 | B11: GGLL | C11: GOOGL | D11: 90.541679 | E11: 16.779835 | F11: 21017 | G11: -56586 | H11: =D11*F11 | I11: =E11*G11 | J11: =H11-I11 | K11: 0 | L11: -17300.959 | M11: 13007.415 | N11: =-I11*K11/252 | O11: 0 | P11: =SUM($N$2:N11)
A12: 44944 | B12: GGLL | C12: GOOGL | D12: 90.373077 | E12: 16.704992 | F12: 21017 | G12: -56586 | H12: =D12*F12 | I12: =E12*G12 | J12: =H12-I12 | K12: 0 | L12: -3543.508 | M12: 4235.035 | N12: =-I12*K12/252 | O12: 0 | P12: =SUM($N$2:N12)
A13: 44945 | B13: GGLL | C13: GOOGL | D13: 92.287254 | E13: 17.26898 | F13: 21017 | G13: -56586 | H13: =D13*F13 | I13: =E13*G13 | J13: =H13-I13 | K13: 0 | L13: 40230.257 | M13: -31913.81 | N13: =-I13*K13/252 | O13: 0 | P13: =SUM($N$2:N13)
... A21: 44957 | B21: GGLL | C21: GOOGL | D21: 98.029778 | E21: 18.79612 | F21: 20673 | G21: -53835 | H21: =D21*F21 | I21: =E21*G21 | J21: =H21-I21 | K21: 0 | L21: 38956.505 | M21: -26189.484 | N21: =-I21*K21/252 | O21: 0 | P21: =SUM($N$2:N21)

Sheet KWEB_CWEB
A1: date | B1: etf | C1: under | D1: KWEB Price | E1: CWEB Price | F1: long_sh | G1: short_sh | H1: long_notional_usd | I1: short_notional_usd | J1: gross_notional_usd | K1: borrow_rate_annual | L1: daily_long_pnl_usd | M1: daily_short_pnl_usd | N1: daily_borrow_cost_usd | O1: is_rebal | P1: cum_borrow_cost_usd
A2: 44929 | B2: CWEB | C2: KWEB | D2: 28.488829 | E2: 50.575115 | F2: 14605 | G2: -4138 | H2: =D2*F2 | I2: =E2*G2 | J2: =H2-I2 | K2: -0.02 | L2: 0 | M2: 0 | N2: =-I2*K2/252 | O2: 1 | P2: =SUM($N$2:N2)
A3: 44930 | B3: CWEB | C3: KWEB | D3: 30.997282 | E3: 59.489017 | F3: 14605 | G3: -4138 | H3: =D3*F3 | I3: =E3*G3 | J3: =H3-I3 | K3: -0.02 | L3: 0 | M3: 0 | N3: =-I3*K3/252 | O3: 0 | P3: =SUM($N$2:N3)
A4: 44931 | B4: CWEB | C4: KWEB | D4: 31.140619 | E4: 60.146305 | F4: 14605 | G4: -4138 | H4: =D4*F4 | I4: =E4*G4 | J4: =H4-I4 | K4: -0.02 | L4: 2093.4405 | M4: -2719.8561 | N4: =-I4*K4/252 | O4: 0 | P4: =SUM($N$2:N4)
A5: 44932 | B5: CWEB | C5: KWEB | D5: 30.970402 | E5: 59.434998 | F5: 14605 | G5: -4138 | H5: =D5*F5 | I5: =E5*G5 | J5: =H5-I5 | K5: -0.02 | L5: -2486.0268 | M5: 2943.3905 | N5: =-I5*K5/252 | O5: 1 | P5: =SUM($N$2:N5)
A6: 44935 | B6: CWEB | C6: KWEB | D6: 31.006239 | E6: 59.543041 | F6: 14605 | G6: -3828 | H6: =D6*F6 | I6: =E6*G6 | J6: =H6-I6 | K6: -0.02 | L6: 523.40192 | M6: -413.59117 | N6: =-I6*K6/252 | O6: 0 | P6: =SUM($N$2:N6)
A7: 44936 | B7: CWEB | C7: KWEB | D7: 31.391468 | E7: 61.037701 | F7: 14605 | G7: -3828 | H7: =D7*F7 | I7: =E7*G7 | J7: =H7-I7 | K7: -0.02 | L7: 5626.2712 | M7: -5721.5563 | N7: =-I7*K7/252 | O7: 0 | P7: =SUM($N$2:N7)
A8: 44937 | B8: CWEB | C8: KWEB | D8: 31.230211 | E8: 60.3624 | F8: 14605 | G8: -3828 | H8: =D8*F8 | I8: =E8*G8 | J8: =H8-I8 | K8: -0.02 | L8: -2355.1554 | M8: 2585.0507 | N8: =-I8*K8/252 | O8: 0 | P8: =SUM($N$2:N8)
A9: 44938 | B9: CWEB | C9: KWEB | D9: 30.80019 | E9: 58.57962 | F9: 14605 | G9: -3828 | H9: =D9*F9 | I9: =E9*G9 | J9: =H9-I9 | K9: -0.02 | L9: -6280.4609 | M9: 6824.4807 | N9: =-I9*K9/252 | O9: 0 | P9: =SUM($N$2:N9)
A10: 44939 | B10: CWEB | C10: KWEB | D10: 31.696062 | E10: 61.83905 | F10: 14605 | G10: -3828 | H10: =D10*F10 | I10: =E10*G10 | J10: =H10-I10 | K10: -0.02 | L10: 13084.212 | M10: -12477.098 | N10: =-I10*K10/252 | O10: 1 | P10: =SUM($N$2:N10)
A11: 44943 | B11: CWEB | C11: KWEB | D11: 30.629971 | E11: 57.922333 | F11: 14190 | G11: -3658 | H11: =D11*F11 | I11: =E11*G11 | J11: =H11-I11 | K11: -0.02 | L11: -15127.839 | M11: 14327.353 | N11: =-I11*K11/252 | O11: 0 | P11: =SUM($N$2:N11)
A12: 44944 | B12: CWEB | C12: KWEB | D12: 29.850561 | E12: 55.023071 | F12: 14190 | G12: -3658 | H12: =D12*F12 | I12: =E12*G12 | J12: =H12-I12 | K12: -0.02 | L12: -11059.82 | M12: 10605.498 | N12: =-I12*K12/252 | O12: 0 | P12: =SUM($N$2:N12)
A13: 44945 | B13: CWEB | C13: KWEB | D13: 30.406 | E13: 56.823849 | F13: 14190 | G13: -3658 | H13: =D13*F13 | I13: =E13*G13 | J13: =H13-I13 | K13: -0.02 | L13: 7881.6793 | M13: -6587.2439 | N13: =-I13*K13/252 | O13: 0 | P13: =SUM($N$2:N13)
... A21: 44957 | B21: CWEB | C21: KWEB | D21: 30.34329 | E21: 56.427673 | F21: 14867 | G21: -3791 | H21: =D21*F21 | I21: =E21*G21 | J21: =H21-I21 | K21: -0.02 | L21: -3196.5774 | M21: 2867.2561 | N21: =-I21*K21/252 | O21: 0 | P21: =SUM($N$2:N21)

Sheet META_FBL
A1: date | B1: etf | C1: under | D1: META Price | E1: FBL Price | F1: long_sh | G1: short_sh | H1: long_notional_usd | I1: short_notional_usd | J1: gross_notional_usd | K1: borrow_rate_annual | L1: daily_long_pnl_usd | M1: daily_short_pnl_usd | N1: daily_borrow_cost_usd | O1: is_rebal | P1: cum_borrow_cost_usd
A2: 44929 | B2: FBL | C2: META | D2: 123.76872 | E2: 3.6421933 | F2: 25964 | G2: -441819 | H2: =D2*F2 | I2: =E2*G2 | J2: =H2-I2 | K2: -0.01 | L2: 0 | M2: 0 | N2: =-I2*K2/252 | O2: 1 | P2: =SUM($N$2:N2)
A3: 44930 | B3: FBL | C3: META | D3: 126.37826 | E3: 3.7544703 | F3: 25964 | G3: -441819 | H3: =D3*F3 | I3: =E3*G3 | J3: =H3-I3 | K3: -0.01 | L3: 0 | M3: 0 | N3: =-I3*K3/252 | O3: 0 | P3: =SUM($N$2:N3)
A4: 44931 | B4: FBL | C4: META | D4: 125.95161 | E4: 3.7375963 | F4: 25964 | G4: -441819 | H4: =D4*F4 | I4: =E4*G4 | J4: =H4-I4 | K4: -0.01 | L4: -11077.567 | M4: 7455.2869 | N4: =-I4*K4/252 | O4: 0 | P4: =SUM($N$2:N4)
A5: 44932 | B5: FBL | C5: META | D5: 129.00763 | E5: 3.8688245 | F5: 25964 | G5: -441819 | H5: =D5*F5 | I5: =E5*G5 | J5: =H5-I5 | K5: -0.01 | L5: 79346.572 | M5: -57979.116 | N5: =-I5*K5/252 | O5: 1 | P5: =SUM($N$2:N5)
A6: 44935 | B6: FBL | C6: META | D6: 128.4619 | E6: 3.8440323 | F6: 25964 | G6: -441819 | H6: =D6*F6 | I6: =E6*G6 | J6: =H6-I6 | K6: -0.01 | L6: -14169.349 | M6: 10953.663 | N6: =-I6*K6/252 | O6: 0 | P6: =SUM($N$2:N6)
A7: 44936 | B7: FBL | C7: META | D7: 131.9545 | E7: 3.9903171 | F7: 25964 | G7: -441819 | H7: =D7*F7 | I7: =E7*G7 | J7: =H7-I7 | K7: -0.01 | L7: 90681.853 | M7: -64631.412 | N7: =-I7*K7/252 | O7: 0 | P7: =SUM($N$2:N7)
A8: 44937 | B8: FBL | C8: META | D8: 131.85529 | E8: 3.9940815 | F8: 25964 | G8: -441819 | H8: =D8*F8 | I8: =E8*G8 | J8: =H8-I8 | K8: -0.01 | L8: -2575.9572 | M8: -1663.1794 | N8: =-I8*K8/252 | O8: 0 | P8: =SUM($N$2:N8)
A9: 44938 | B9: FBL | C9: META | D9: 135.64554 | E9: 4.1743741 | F9: 25964 | G9: -441819 | H9: =D9*F9 | I9: =E9*G9 | J9: =H9-I9 | K9: -0.01 | L9: 98410.121 | M9: -79656.699 | N9: =-I9*K9/252 | O9: 0 | P9: =SUM($N$2:N9)
A10: 44939 | B10: FBL | C10: META | D10: 135.91341 | E10: 4.1794362 | F10: 25964 | G10: -441819 | H10: =D10*F10 | I10: =E10*G10 | J10: =H10-I10 | K10: -0.01 | L10: 6954.9258 | M10: -2236.5334 | N10: =-I10*K10/252 | O10: 1 | P10: =SUM($N$2:N10)
A11: 44943 | B11: FBL | C11: META | D11: 134.30602 | E11: 4.1036329 | F11: 25557 | G11: -416177 | H11: =D11*F11 | I11: =E11*G11 | J11: =H11-I11 | K11: -0.01 | L11: -41080.101 | M11: 31547.582 | N11: =-I11*K11/252 | O11: 0 | P11: =SUM($N$2:N11)
A12: 44944 | B12: FBL | C12: META | D12: 131.98428 | E12: 4.0005713 | F12: 25557 | G12: -416177 | H12: =D12*F12 | I12: =E12*G12 | J12: =H12-I12 | K12: -0.01 | L12: -59336.494 | M12: 42891.899 | N12: =-I12*K12/252 | O12: 0 | P12: =SUM($N$2:N12)
A13: 44945 | B13: FBL | C13: META | D13: 135.08989 | E13: 4.1395874 | F13: 25557 | G13: -416177 | H13: =D13*F13 | I13: =E13*G13 | J13: =H13-I13 | K13: -0.01 | L13: 79369.975 | M13: -57855.325 | N13: =-I13*K13/252 | O13: 0 | P13: =SUM($N$2:N13)
... A21: 44957 | B21: FBL | C21: META | D21: 147.81004 | E21: 4.7035689 | F21: 24480 | G21: -380714 | H21: =D21*F21 | I21: =E21*G21 | J21: =H21-I21 | K21: -0.01 | L21: 46392.319 | M21: -30737.023 | N21: =-I21*K21/252 | O21: 0 | P21: =SUM($N$2:N21)

Sheet MSFT_MSFU
A1: date | B1: etf | C1: under | D1: MSFT Price | E1: MSFU Price | F1: long_sh | G1: short_sh | H1: long_notional_usd | I1: short_notional_usd | J1: gross_notional_usd | K1: borrow_rate_annual | L1: daily_long_pnl_usd | M1: daily_short_pnl_usd | N1: daily_borrow_cost_usd | O1: is_rebal | P1: cum_borrow_cost_usd
A2: 44929 | B2: MSFU | C2: MSFT | D2: 233.45279 | E2: 18.773363 | F2: 8314 | G2: -51898 | H2: =D2*F2 | I2: =E2*G2 | J2: =H2-I2 | K2: -0.005 | L2: 0 | M2: 0 | N2: =-I2*K2/252 | O2: 1 | P2: =SUM($N$2:N2)
A3: 44930 | B3: MSFU | C3: MSFT | D3: 223.24081 | E3: 17.523445 | F3: 8314 | G3: -51898 | H3: =D3*F3 | I3: =E3*G3 | J3: =H3-I3 | K3: -0.005 | L3: 0 | M3: 0 | N3: =-I3*K3/252 | O3: 0 | P3: =SUM($N$2:N3)
A4: 44931 | B4: MSFU | C4: MSFT | D4: 216.62447 | E4: 16.761297 | F4: 8314 | G4: -51898 | H4: =D4*F4 | I4: =E4*G4 | J4: =H4-I4 | K4: -0.005 | L4: -55008.319 | M4: 39553.952 | N4: =-I4*K4/252 | O4: 0 | P4: =SUM($N$2:N4)
A5: 44932 | B5: MSFU | C5: MSFT | D5: 219.17747 | E5: 17.012804 | F5: 8314 | G5: -51898 | H5: =D5*F5 | I5: =E5*G5 | J5: =H5-I5 | K5: -0.005 | L5: 21225.717 | M5: -13052.7 | N5: =-I5*K5/252 | O5: 1 | P5: =SUM($N$2:N5)
A6: 44935 | B6: MSFU | C6: MSFT | D6: 221.31146 | E6: 17.309191 | F6: 8314 | G6: -53770 | H6: =D6*F6 | I6: =E6*G6 | J6: =H6-I6 | K6: -0.005 | L6: 17741.971 | M6: -15936.714 | N6: =-I6*K6/252 | O6: 0 | P6: =SUM($N$2:N6)
A7: 44936 | B7: MSFU | C7: MSFT | D7: 222.99724 | E7: 17.462469 | F7: 8314 | G7: -53770 | H7: =D7*F7 | I7: =E7*G7 | J7: =H7-I7 | K7: -0.005 | L7: 14015.54 | M7: -8241.7769 | N7: =-I7*K7/252 | O7: 0 | P7: =SUM($N$2:N7)
A8: 44937 | B8: MSFU | C8: MSFT | D8: 229.74025 | E8: 18.255104 | F8: 8314 | G8: -53770 | H8: =D8*F8 | I8: =E8*G8 | J8: =H8-I8 | K8: -0.005 | L8: 56061.397 | M8: -42619.982 | N8: =-I8*K8/252 | O8: 0 | P8: =SUM($N$2:N8)
A9: 44938 | B9: MSFU | C9: MSFT | D9: 232.41016 | E9: 18.590446 | F9: 8314 | G9: -53770 | H9: =D9*F9 | I9: =E9*G9 | J9: =H9-I9 | K9: -0.005 | L9: 22197.604 | M9: -18031.361 | N9: =-I9*K9/252 | O9: 0 | P9: =SUM($N$2:N9)
A10: 44939 | B10: MSFU | C10: MSFT | D10: 233.11172 | E10: 18.651419 | F10: 8314 | G10: -53770 | H10: =D10*F10 | I10: =E10*G10 | J10: =H10-I10 | K10: -0.005 | L10: 5832.8414 | M10: -3278.4759 | N10: =-I10*K10/252 | O10: 1 | P10: =SUM($N$2:N10)
A11: 44943 | B11: MSFU | C11: MSFT | D11: 234.20312 | E11: 18.772512 | F11: 8999 | G11: -56464 | H11: =D11*F11 | I11: =E11*G11 | J11: =H11-I11 | K11: -0.005 | L11: 9821.5099 | M11: -6837.4375 | N11: =-I11*K11/252 | O11: 0 | P11: =SUM($N$2:N11)
A12: 44944 | B12: MSFU | C12: MSFT | D12: 229.77922 | E12: 18.249172 | F12: 8999 | G12: -56464 | H12: =D12*F12 | I12: =E12*G12 | J12: =H12-I12 | K12: -0.005 | L12: -39810.716 | M12: 29549.882 | N12: =-I12*K12/252 | O12: 0 | P12: =SUM($N$2:N12)
A13: 44945 | B13: MSFU | C13: MSFT | D13: 225.99841 | E13: 17.793579 | F13: 8999 | G13: -56464 | H13: =D13*F13 | I13: =E13*G13 | J13: =H13-I13 | K13: -0.005 | L13: -34023.487 | M13: 25724.609 | N13: =-I13*K13/252 | O13: 0 | P13: =SUM($N$2:N13)
... A21: 44957 | B21: MSFU | C21: MSFT | D21: 241.47227 | E21: 19.604099 | F21: 9205 | G21: -56905 | H21: =D21*F21 | I21: =E21*G21 | J21: =H21-I21 | K21: -0.005 | L21: 45744.367 | M21: -33732.098 | N21: =-I21*K21/252 | O21: 0 | P21: =SUM($N$2:N21)

Sheet NVDA_NVDL
A1: date | B1: etf | C1: under | D1: NVDA Price | E1: NVDL Price | F1: long_sh | G1: short_sh | H1: long_notional_usd | I1: short_notional_usd | J1: gross_notional_usd | K1: borrow_rate_annual | L1: daily_long_pnl_usd | M1: daily_short_pnl_usd | N1: daily_borrow_cost_usd | O1: is_rebal | P1: cum_borrow_cost_usd
A2: 44929 | B2: NVDL | C2: NVDA | D2: 14.299909 | E2: 2.8854489 | F2: 307781 | G2: -767265 | H2: =D2*F2 | I2: =E2*G2 | J2: =H2-I2 | K2: 0 | L2: 0 | M2: 0 | N2: =-I2*K2/252 | O2: 1 | P2: =SUM($N$2:N2)
A3: 44930 | B3: NVDL | C3: NVDA | D3: 14.733453 | E3: 2.8426468 | F3: 307781 | G3: -767265 | H3: =D3*F3 | I3: =E3*G3 | J3: =H3-I3 | K3: 0 | L3: 0 | M3: 0 | N3: =-I3*K3/252 | O3: 0 | P3: =SUM($N$2:N3)
A4: 44931 | B4: NVDL | C4: NVDA | D4: 14.249963 | E4: 2.7118435 | F4: 307781 | G4: -767265 | H4: =D4*F4 | I4: =E4*G4 | J4: =H4-I4 | K4: 0 | L4: -148809.03 | M4: 100360.83 | N4: =-I4*K4/252 | O4: 0 | P4: =SUM($N$2:N4)
A5: 44932 | B5: NVDL | C5: NVDA | D5: 14.843339 | E5: 2.8748236 | F5: 307781 | G5: -767265 | H5: =D5*F5 | I5: =E5*G5 | J5: =H5-I5 | K5: 0 | L5: 182629.91 | M5: -125048.91 | N5: =-I5*K5/252 | O5: 1 | P5: =SUM($N$2:N5)
A6: 44935 | B6: NVDL | C6: NVDA | D6: 15.611526 | E6: 3.1114364 | F6: 307781 | G6: -799366 | H6: =D6*F6 | I6: =E6*G6 | J6: =H6-I6 | K6: 0 | L6: 236433.52 | M6: -189140.22 | N6: =-I6*K6/252 | O6: 0 | P6: =SUM($N$2:N6)
A7: 44936 | B7: NVDL | C7: NVDA | D7: 15.89223 | E7: 3.1858172 | F7: 307781 | G7: -799366 | H7: =D7*F7 | I7: =E7*G7 | J7: =H7-I7 | K7: 0 | L7: 86395.218 | M7: -59457.542 | N7: =-I7*K7/252 | O7: 0 | P7: =SUM($N$2:N7)
A8: 44937 | B8: NVDL | C8: NVDA | D8: 15.984131 | E8: 3.2311642 | F8: 307781 | G8: -799366 | H8: =D8*F8 | I8: =E8*G8 | J8: =H8-I8 | K8: 0 | L8: 28285.328 | M8: -36248.83 | N8: =-I8*K8/252 | O8: 0 | P8: =SUM($N$2:N8)
A9: 44938 | B9: NVDL | C9: NVDA | D9: 16.493593 | E9: 3.3652606 | F9: 307781 | G9: -799366 | H9: =D9*F9 | I9: =E9*G9 | J9: =H9-I9 | K9: 0 | L9: 156802.83 | M9: -107192.09 | N9: =-I9*K9/252 | O9: 0 | P9: =SUM($N$2:N9)
A10: 44939 | B10: NVDL | C10: NVDA | D10: 16.881191 | E10: 3.4785526 | F10: 307781 | G10: -799366 | H10: =D10*F10 | I10: =E10*G10 | J10: =H10-I10 | K10: 0 | L10: 119295.31 | M10: -90561.756 | N10: =-I10*K10/252 | O10: 1 | P10: =SUM($N$2:N10)
A11: 44943 | B11: NVDL | C11: NVDA | D11: 17.683338 | E11: 3.7115738 | F11: 281812 | G11: -687936 | H11: =D11*F11 | I11: =E11*G11 | J11: =H11-I11 | K11: 0 | L11: 226054.63 | M11: -160303.71 | N11: =-I11*K11/252 | O11: 0 | P11: =SUM($N$2:N11)
A12: 44944 | B12: NVDL | C12: NVDA | D12: 17.358683 | E12: 3.6231244 | F12: 281812 | G12: -687936 | H12: =D12*F12 | I12: =E12*G12 | J12: =H12-I12 | K12: 0 | L12: -91491.825 | M12: 60847.58 | N12: =-I12*K12/252 | O12: 0 | P12: =SUM($N$2:N12)
A13: 44945 | B13: NVDL | C13: NVDA | D13: 16.747332 | E13: 3.4321585 | F13: 281812 | G13: -687936 | H13: =D13*F13 | I13: =E13*G13 | J13: =H13-I13 | K13: 0 | L13: -172286.05 | M13: 131372.31 | N13: =-I13*K13/252 | O13: 0 | P13: =SUM($N$2:N13)
... A21: 44957 | B21: NVDL | C21: NVDA | D21: 19.516407 | E21: 4.2713037 | F21: 248132 | G21: -555379 | H21: =D21*F21 | I21: =E21*G21 | J21: =H21-I21 | K21: 0 | L21: 92951.532 | M21: -42390.328 | N21: =-I21*K21/252 | O21: 0 | P21: =SUM($N$2:N21)

Sheet SOXX_SOXL
A1: date | B1: etf | C1: under | D1: SOXX Price | E1: SOXL Price | F1: long_sh | G1: short_sh | H1: long_notional_usd | I1: short_notional_usd | J1: gross_notional_usd | K1: borrow_rate_annual | L1: daily_long_pnl_usd | M1: daily_short_pnl_usd | N1: daily_borrow_cost_usd | O1: is_rebal | P1: cum_borrow_cost_usd
A2: 44929 | B2: SOXL | C2: SOXX | D2: 112.21332 | E2: 9.1589022 | F2: 8941 | G2: -36957 | H2: =D2*F2 | I2: =E2*G2 | J2: =H2-I2 | K2: -0.0175 | L2: 0 | M2: 0 | N2: =-I2*K2/252 | O2: 1 | P2: =SUM($N$2:N2)
A3: 44930 | B3: SOXL | C3: SOXX | D3: 115.10177 | E3: 9.8536491 | F3: 8941 | G3: -36957 | H3: =D3*F3 | I3: =E3*G3 | J3: =H3-I3 | K3: -0.0175 | L3: 0 | M3: 0 | N3: =-I3*K3/252 | O3: 0 | P3: =SUM($N$2:N3)
A4: 44931 | B4: SOXL | C4: SOXX | D4: 113.16093 | E4: 9.3643904 | F4: 8941 | G4: -36957 | H4: =D4*F4 | I4: =E4*G4 | J4: =H4-I4 | K4: -0.0175 | L4: -17352.997 | M4: 18081.536 | N4: =-I4*K4/252 | O4: 0 | P4: =SUM($N$2:N4)
A5: 44932 | B5: SOXL | C5: SOXX | D5: 118.4266 | E5: 10.636461 | F5: 8941 | G5: -36957 | H5: =D5*F5 | I5: =E5*G5 | J5: =H5-I5 | K5: -0.0175 | L5: 47080.294 | M5: -47011.924 | N5: =-I5*K5/252 | O5: 1 | P5: =SUM($N$2:N5)
A6: 44935 | B6: SOXL | C6: SOXX | D6: 120.60839 | E6: 11.28228 | F6: 8941 | G6: -33586 | H6: =D6*F6 | I6: =E6*G6 | J6: =H6-I6 | K6: -0.0175 | L6: 19507.413 | M6: -21690.467 | N6: =-I6*K6/252 | O6: 0 | P6: =SUM($N$2:N6)
A7: 44936 | B7: SOXL | C7: SOXX | D7: 122.16821 | E7: 11.712828 | F7: 8941 | G7: -33586 | H7: =D7*F7 | I7: =E7*G7 | J7: =H7-I7 | K7: -0.0175 | L7: 13946.369 | M7: -14460.376 | N7: =-I7*K7/252 | O7: 0 | P7: =SUM($N$2:N7)
A8: 44937 | B8: SOXL | C8: SOXX | D8: 123.74432 | E8: 12.133589 | F8: 8941 | G8: -33586 | H8: =D8*F8 | I8: =E8*G8 | J8: =H8-I8 | K8: -0.0175 | L8: 14091.939 | M8: -14131.683 | N8: =-I8*K8/252 | O8: 0 | P8: =SUM($N$2:N8)
A9: 44938 | B9: SOXL | C9: SOXX | D9: 125.24878 | E9: 12.544563 | F9: 8941 | G9: -33586 | H9: =D9*F9 | I9: =E9*G9 | J9: =H9-I9 | K9: -0.0175 | L9: 13451.405 | M9: -13802.99 | N9: =-I9*K9/252 | O9: 0 | P9: =SUM($N$2:N9)
A10: 44939 | B10: SOXL | C10: SOXX | D10: 125.76659 | E10: 12.671772 | F10: 8941 | G10: -33586 | H10: =D10*F10 | I10: =E10*G10 | J10: =H10-I10 | K10: -0.0175 | L10: 4629.7124 | M10: -4272.4317 | N10: =-I10*K10/252 | O10: 1 | P10: =SUM($N$2:N10)
A11: 44943 | B11: SOXL | C11: SOXX | D11: 125.90984 | E11: 12.779409 | F11: 8623 | G11: -28873 | H11: =D11*F11 | I11: =E11*G11 | J11: =H11-I11 | K11: -0.0175 | L11: 1235.2405 | M11: -3107.8148 | N11: =-I11*K11/252 | O11: 0 | P11: =SUM($N$2:N11)
A12: 44944 | B12: SOXL | C12: SOXX | D12: 125.24878 | E12: 12.544563 | F12: 8623 | G12: -28873 | H12: =D12*F12 | I12: =E12*G12 | J12: =H12-I12 | K12: -0.0175 | L12: -5700.2904 | M12: 6780.7119 | N12: =-I12*K12/252 | O12: 0 | P12: =SUM($N$2:N12)
A13: 44945 | B13: SOXL | C13: SOXX | D13: 121.73511 | E13: 11.517124 | F13: 8623 | G13: -28873 | H13: =D13*F13 | I13: =E13*G13 | J13: =H13-I13 | K13: -0.0175 | L13: -30298.393 | M13: 29665.25 | N13: =-I13*K13/252 | O13: 0 | P13: =SUM($N$2:N13)
... A21: 44957 | B21: SOXL | C21: SOXX | D21: 131.45551 | E21: 14.208042 | F21: 8680 | G21: -26485 | H21: =D21*F21 | I21: =E21*G21 | J21: =H21-I21 | K21: -0.0175 | L21: 20888.104 | M21: -18659.521 | N21: =-I21*K21/252 | O21: 0 | P21: =SUM($N$2:N21)

Sheet SOXX_SOXS
A1: date | B1: etf | C1: under | D1: SOXX Price | E1: SOXS Price | F1: long_sh | G1: short_sh | H1: long_notional_usd | I1: short_notional_usd | J1: gross_notional_usd | K1: borrow_rate_annual | L1: daily_long_pnl_usd | M1: daily_short_pnl_usd | N1: daily_borrow_cost_usd | O1: is_rebal | P1: cum_borrow_cost_usd
A2: 44929 | B2: SOXS | C2: SOXX | D2: 0 | E2: 0 | F2: -6997 | G2: -37 | H2: =D2*F2 | I2: =E2*G2 | J2: =H2-I2 | K2: 0.07 | L2: 0 | M2: 0 | N2: =-I2*K2/252 | O2: 1 | P2: =SUM($N$2:N2)
A3: 44930 | B3: SOXS | C3: SOXX | D3: 0 | E3: 0 | F3: -6997 | G3: -37 | H3: =D3*F3 | I3: =E3*G3 | J3: =H3-I3 | K3: 0.07 | L3: 0 | M3: 0 | N3: =-I3*K3/252 | O3: 0 | P3: =SUM($N$2:N3)
A4: 44931 | B4: SOXS | C4: SOXX | D4: 0 | E4: 0 | F4: -6997 | G4: -37 | H4: =D4*F4 | I4: =E4*G4 | J4: =H4-I4 | K4: 0.07 | L4: 13580.016 | M4: -13327.154 | N4: =-I4*K4/252 | O4: 0 | P4: =SUM($N$2:N4)
A5: 44932 | B5: SOXS | C5: SOXX | D5: 0 | E5: 0 | F5: -6997 | G5: -37 | H5: =D5*F5 | I5: =E5*G5 | J5: =H5-I5 | K5: 0.07 | L5: -36843.845 | M5: 35667.837 | N5: =-I5*K5/252 | O5: 1 | P5: =SUM($N$2:N5)
A6: 44935 | B6: SOXS | C6: SOXX | D6: 0 | E6: 0 | F6: -6997 | G6: -37 | H6: =D6*F6 | I6: =E6*G6 | J6: =H6-I6 | K6: 0.07 | L6: -15266.007 | M6: 12747.692 | N6: =-I6*K6/252 | O6: 0 | P6: =SUM($N$2:N6)
A7: 44936 | B7: SOXS | C7: SOXX | D7: 0 | E7: 0 | F7: -6997 | G7: -37 | H7: =D7*F7 | I7: =E7*G7 | J7: =H7-I7 | K7: 0.07 | L7: -10914.075 | M7: 7983.4185 | N7: =-I7*K7/252 | O7: 0 | P7: =SUM($N$2:N7)
A8: 44937 | B8: SOXS | C8: SOXX | D8: 0 | E8: 0 | F8: -6997 | G8: -37 | H8: =D8*F8 | I8: =E8*G8 | J8: =H8-I8 | K8: 0.07 | L8: -11027.994 | M8: 7468.3452 | N8: =-I8*K8/252 | O8: 0 | P8: =SUM($N$2:N8)
A9: 44938 | B9: SOXS | C9: SOXX | D9: 0 | E9: 0 | F9: -6997 | G9: -37 | H9: =D9*F9 | I9: =E9*G9 | J9: =H9-I9 | K9: 0.07 | L9: -10526.729 | M9: 6245.105 | N9: =-I9*K9/252 | O9: 0 | P9: =SUM($N$2:N9)
A10: 44939 | B10: SOXS | C10: SOXX | D10: 0 | E10: 0 | F10: -6997 | G10: -37 | H10: =D10*F10 | I10: =E10*G10 | J10: =H10-I10 | K10: 0.07 | L10: -3623.0956 | M10: 1867.1089 | N10: =-I10*K10/252 | O10: 1 | P10: =SUM($N$2:N10)
A11: 44943 | B11: SOXS | C11: SOXX | D11: 0 | E11: 0 | F11: -6748 | G11: -57 | H11: =D11*F11 | I11: =E11*G11 | J11: =H11-I11 | K11: 0.07 | L11: -966.64771 | M11: 2578.6934 | N11: =-I11*K11/252 | O11: 0 | P11: =SUM($N$2:N11)
A12: 44944 | B12: SOXS | C12: SOXX | D12: 0 | E12: 0 | F12: -6748 | G12: -57 | H12: =D12*F12 | I12: =E12*G12 | J12: =H12-I12 | K12: 0.07 | L12: 4460.8094 | M12: -5157.5259 | N12: =-I12*K12/252 | O12: 0 | P12: =SUM($N$2:N12)
A13: 44945 | B13: SOXS | C13: SOXX | D13: 0 | E13: 0 | F13: -6748 | G13: -57 | H13: =D13*F13 | I13: =E13*G13 | J13: =H13-I13 | K13: 0.07 | L13: 23710.258 | M13: -24200.786 | N13: =-I13*K13/252 | O13: 0 | P13: =SUM($N$2:N13)
... A21: 44957 | B21: SOXS | C21: SOXX | D21: 0 | E21: 0 | F21: -6792 | G21: -73 | H21: =D21*F21 | I21: =E21*G21 | J21: =H21-I21 | K21: 0.07 | L21: -16344.701 | M21: 16894.225 | N21: =-I21*K21/252 | O21: 0 | P21: =SUM($N$2:N21)

Sheet SPHB_HIBL
A1: date | B1: etf | C1: under | D1: SPHB Price | E1: HIBL Price | F1: long_sh | G1: short_sh | H1: long_notional_usd | I1: short_notional_usd | J1: gross_notional_usd | K1: borrow_rate_annual | L1: daily_long_pnl_usd | M1: daily_short_pnl_usd | N1: daily_borrow_cost_usd | O1: is_rebal | P1: cum_borrow_cost_usd
A2: 44929 | B2: HIBL | C2: SPHB | D2: 60.59737 | E2: 22.451878 | F2: 6521 | G2: -5851 | H2: =D2*F2 | I2: =E2*G2 | J2: =H2-I2 | K2: 0.12 | L2: 0 | M2: 0 | N2: =-I2*K2/252 | O2: 1 | P2: =SUM($N$2:N2)
A3: 44930 | B3: HIBL | C3: SPHB | D3: 62.313122 | E3: 24.359615 | F3: 6521 | G3: -5851 | H3: =D3*F3 | I3: =E3*G3 | J3: =H3-I3 | K3: 0.12 | L3: 0 | M3: 0 | N3: =-I3*K3/252 | O3: 0 | P3: =SUM($N$2:N3)
A4: 44931 | B4: HIBL | C4: SPHB | D4: 61.435757 | E4: 23.391367 | F4: 6521 | G4: -5851 | H4: =D4*F4 | I4: =E4*G4 | J4: =H4-I4 | K4: 0.12 | L4: -5721.2979 | M4: 5665.2212 | N4: =-I4*K4/252 | O4: 0 | P4: =SUM($N$2:N4)
A5: 44932 | B5: HIBL | C5: SPHB | D5: 63.112522 | E5: 25.28952 | F5: 6521 | G5: -5851 | H5: =D5*F5 | I5: =E5*G5 | J5: =H5-I5 | K5: 0.12 | L5: 10934.187 | M5: -11106.095 | N5: =-I5*K5/252 | O5: 1 | P5: =SUM($N$2:N5)
A6: 44935 | B6: HIBL | C6: SPHB | D6: 63.970398 | E6: 26.305704 | F6: 6521 | G6: -5410 | H6: =D6*F6 | I6: =E6*G6 | J6: =H6-I6 | K6: 0.12 | L6: 5594.2082 | M6: -5497.5546 | N6: =-I6*K6/252 | O6: 0 | P6: =SUM($N$2:N6)
A7: 44936 | B7: HIBL | C7: SPHB | D7: 64.857529 | E7: 27.331474 | F7: 6521 | G7: -5410 | H7: =D7*F7 | I7: =E7*G7 | J7: =H7-I7 | K7: 0.12 | L7: 5784.9795 | M7: -5549.4167 | N7: =-I7*K7/252 | O7: 0 | P7: =SUM($N$2:N7)
A8: 44937 | B8: HIBL | C8: SPHB | D8: 65.949356 | E8: 28.654428 | F8: 6521 | G8: -5410 | H8: =D8*F8 | I8: =E8*G8 | J8: =H8-I8 | K8: 0.12 | L8: 7119.8064 | M8: -7157.1821 | N8: =-I8*K8/252 | O8: 0 | P8: =SUM($N$2:N8)
A9: 44938 | B9: HIBL | C9: SPHB | D9: 66.573288 | E9: 29.565157 | F9: 6521 | G9: -5410 | H9: =D9*F9 | I9: =E9*G9 | J9: =H9-I9 | K9: 0.12 | L9: 4068.6598 | M9: -4927.0409 | N9: =-I9*K9/252 | O9: 0 | P9: =SUM($N$2:N9)
A10: 44939 | B10: HIBL | C10: SPHB | D10: 66.875488 | E10: 29.910273 | F10: 6521 | G10: -5410 | H10: =D10*F10 | I10: =E10*G10 | J10: =H10-I10 | K10: 0.12 | L10: 1970.6483 | M10: -1867.0757 | N10: =-I10*K10/252 | O10: 1 | P10: =SUM($N$2:N10)
A11: 44943 | B11: HIBL | C11: SPHB | D11: 67.20694 | E11: 30.370432 | F11: 6387 | G11: -4747 | H11: =D11*F11 | I11: =E11*G11 | J11: =H11-I11 | K11: 0.12 | L11: 2116.9802 | M11: -2184.3762 | N11: =-I11*K11/252 | O11: 0 | P11: =SUM($N$2:N11)
A12: 44944 | B12: HIBL | C12: SPHB | D12: 66.456284 | E12: 29.306314 | F12: 6387 | G12: -4747 | H12: =D12*F12 | I12: =E12*G12 | J12: =H12-I12 | K12: 0.12 | L12: -4794.4407 | M12: 5051.3654 | N12: =-I12*K12/252 | O12: 0 | P12: =SUM($N$2:N12)
A13: 44945 | B13: HIBL | C13: SPHB | D13: 65.159714 | E13: 27.494446 | F13: 6387 | G13: -4747 | H13: =D13*F13 | I13: =E13*G13 | J13: =H13-I13 | K13: 0.12 | L13: -8281.1915 | M13: 8600.9406 | N13: =-I13*K13/252 | O13: 0 | P13: =SUM($N$2:N13)
... A21: 44957 | B21: HIBL | C21: SPHB | D21: 70.579956 | E21: 34.607719 | F21: 6429 | G21: -4351 | H21: =D21*F21 | I21: =E21*G21 | J21: =H21-I21 | K21: 0.12 | L21: 10215.857 | M21: -9718.7614 | N21: =-I21*K21/252 | O21: 0 | P21: =SUM($N$2:N21)

Sheet TSLA_TSLL
A1: date | B1: etf | C1: under | D1: TSLA Price | E1: TSLL Price | F1: long_sh | G1: short_sh | H1: long_notional_usd | I1: short_notional_usd | J1: gross_notional_usd | K1: borrow_rate_annual | L1: daily_long_pnl_usd | M1: daily_short_pnl_usd | N1: daily_borrow_cost_usd | O1: is_rebal | P1: cum_borrow_cost_usd
A2: 44929 | B2: TSLL | C2: TSLA | D2: 108.1 | E2: 4.4069343 | F2: 16893 | G2: -207812 | H2: =D2*F2 | I2: =E2*G2 | J2: =H2-I2 | K2: 0.01 | L2: 0 | M2: 0 | N2: =-I2*K2/252 | O2: 1 | P2: =SUM($N$2:N2)
A3: 44930 | B3: TSLL | C3: TSLA | D3: 113.64 | E3: 4.7445946 | F3: 16893 | G3: -207812 | H3: =D3*F3 | I3: =E3*G3 | J3: =H3-I3 | K3: 0.01 | L3: 0 | M3: 0 | N3: =-I3*K3/252 | O3: 0 | P3: =SUM($N$2:N3)
A4: 44931 | B4: TSLL | C4: TSLA | D4: 110.34 | E4: 4.5454621 | F4: 16893 | G4: -207812 | H4: =D4*F4 | I4: =E4*G4 | J4: =H4-I4 | K4: 0.01 | L4: -55746.952 | M4: 41382.111 | N4: =-I4*K4/252 | O4: 0 | P4: =SUM($N$2:N4)
A5: 44932 | B5: TSLL | C5: TSLA | D5: 113.06 | E5: 4.7099643 | F5: 16893 | G5: -207812 | H5: =D5*F5 | I5: =E5*G5 | J5: =H5-I5 | K5: 0.01 | L5: 45948.981 | M5: -34185.52 | N5: =-I5*K5/252 | O5: 1 | P5: =SUM($N$2:N5)
A6: 44935 | B6: TSLL | C6: TSLA | D6: 119.77 | E6: 5.1255493 | F6: 16893 | G6: -207812 | H6: =D6*F6 | I6: =E6*G6 | J6: =H6-I6 | K6: 0.01 | L6: 113352.01 | M6: -86363.559 | N6: =-I6*K6/252 | O6: 0 | P6: =SUM($N$2:N6)
A7: 44936 | B7: TSLL | C7: TSLA | D7: 118.85 | E7: 5.0736017 | F7: 16893 | G7: -207812 | H7: =D7*F7 | I7: =E7*G7 | J7: =H7-I7 | K7: 0.01 | L7: -15541.529 | M7: 10795.333 | N7: =-I7*K7/252 | O7: 0 | P7: =SUM($N$2:N7)
A8: 44937 | B8: TSLL | C8: TSLA | D8: 123.22 | E8: 5.3419991 | F8: 16893 | G8: -207812 | H8: =D8*F8 | I8: =E8*G8 | J8: =H8-I8 | K8: 0.01 | L8: 73822.456 | M8: -55776.186 | N8: =-I8*K8/252 | O8: 0 | P8: =SUM($N$2:N8)
A9: 44938 | B9: TSLL | C9: TSLA | D9: 123.56 | E9: 5.3593159 | F9: 16893 | G9: -207812 | H9: =D9*F9 | I9: =E9*G9 | J9: =H9-I9 | K9: 0.01 | L9: 5743.5581 | M9: -3598.6426 | N9: =-I9*K9/252 | O9: 0 | P9: =SUM($N$2:N9)
A10: 44939 | B10: TSLL | C10: TSLA | D10: 122.4 | E10: 5.2813935 | F10: 16893 | G10: -207812 | H10: =D10*F10 | I10: =E10*G10 | J10: =H10-I10 | K10: 0.01 | L10: -19595.813 | M10: 16193.198 | N10: =-I10*K10/252 | O10: 1 | P10: =SUM($N$2:N10)
A11: 44943 | B11: TSLL | C11: TSLA | D11: 131.49001 | E11: 5.8701391 | F11: 16126 | G11: -187433 | H11: =D11*F11 | I11: =E11*G11 | J11: =H11-I11 | K11: 0.01 | L11: 146585.4 | M11: -110350.35 | N11: =-I11*K11/252 | O11: 0 | P11: =SUM($N$2:N11)
A12: 44944 | B12: TSLL | C12: TSLA | D12: 128.78 | E12: 5.6969776 | F12: 16126 | G12: -187433 | H12: =D12*F12 | I12: =E12*G12 | J12: =H12-I12 | K12: 0.01 | L12: -43701.568 | M12: 32456.181 | N12: =-I12*K12/252 | O12: 0 | P12: =SUM($N$2:N12)
A13: 44945 | B13: TSLL | C13: TSLA | D13: 127.17 | E13: 5.5757651 | F13: 16126 | G13: -187433 | H13: =D13*F13 | I13: =E13*G13 | J13: =H13-I13 | K13: 0.01 | L13: -25962.87 | M13: 22719.219 | N13: =-I13*K13/252 | O13: 0 | P13: =SUM($N$2:N13)
... A21: 44957 | B21: TSLL | C21: TSLA | D21: 173.22 | E21: 8.7446032 | F21: 11773 | G21: -114993 | H21: =D21*F21 | I21: =E21*G21 | J21: =H21-I21 | K21: 0.01 | L21: 77230.851 | M21: -54758.911 | N21: =-I21*K21/252 | O21: 0 | P21: =SUM($N$2:N21)

Sheet TSLA_TSLQ
A1: date | B1: etf | C1: under | D1: TSLA Price | E1: TSLQ Price | F1: long_sh | G1: short_sh | H1: long_notional_usd | I1: short_notional_usd | J1: gross_notional_usd | K1: borrow_rate_annual | L1: daily_long_pnl_usd | M1: daily_short_pnl_usd | N1: daily_borrow_cost_usd | O1: is_rebal | P1: cum_borrow_cost_usd
A2: 44929 | B2: TSLQ | C2: TSLA | D2: 0 | E2: 0 | F2: -6277 | G2: -302 | H2: =D2*F2 | I2: =E2*G2 | J2: =H2-I2 | K2: -0.02 | L2: 0 | M2: 0 | N2: =-I2*K2/252 | O2: 1 | P2: =SUM($N$2:N2)
A3: 44930 | B3: TSLQ | C3: TSLA | D3: 0 | E3: 0 | F3: -6277 | G3: -302 | H3: =D3*F3 | I3: =E3*G3 | J3: =H3-I3 | K3: -0.02 | L3: 0 | M3: 0 | N3: =-I3*K3/252 | O3: 0 | P3: =SUM($N$2:N3)
A4: 44931 | B4: TSLQ | C4: TSLA | D4: 0 | E4: 0 | F4: -6277 | G4: -302 | H4: =D4*F4 | I4: =E4*G4 | J4: =H4-I4 | K4: -0.02 | L4: 20714.119 | M4: -10111.175 | N4: =-I4*K4/252 | O4: 0 | P4: =SUM($N$2:N4)
A5: 44932 | B5: TSLQ | C5: TSLA | D5: 0 | E5: 0 | F5: -6277 | G5: -302 | H5: =D5*F5 | I5: =E5*G5 | J5: =H5-I5 | K5: -0.02 | L5: -17073.448 | M5: 8649.3213 | N5: =-I5*K5/252 | O5: 1 | P5: =SUM($N$2:N5)
A6: 44935 | B6: TSLQ | C6: TSLA | D6: 0 | E6: 0 | F6: -6277 | G6: -302 | H6: =D6*F6 | I6: =E6*G6 | J6: =H6-I6 | K6: -0.02 | L6: -42118.664 | M6: 20709.562 | N6: =-I6*K6/252 | O6: 0 | P6: =SUM($N$2:N6)
A7: 44936 | B7: TSLQ | C7: TSLA | D7: 0 | E7: 0 | F7: -6277 | G7: -302 | H7: =D7*F7 | I7: =E7*G7 | J7: =H7-I7 | K7: -0.02 | L7: 5774.8285 | M7: -2680.0657 | N7: =-I7*K7/252 | O7: 0 | P7: =SUM($N$2:N7)
A8: 44937 | B8: TSLQ | C8: TSLA | D8: 0 | E8: 0 | F8: -6277 | G8: -302 | H8: =D8*F8 | I8: =E8*G8 | J8: =H8-I8 | K8: -0.02 | L8: -27430.507 | M8: 12344.508 | N8: =-I8*K8/252 | O8: 0 | P8: =SUM($N$2:N8)
A9: 44938 | B9: TSLQ | C9: TSLA | D9: 0 | E9: 0 | F9: -6277 | G9: -302 | H9: =D9*F9 | I9: =E9*G9 | J9: =H9-I9 | K9: -0.02 | L9: -2134.157 | M9: 446.69604 | N9: =-I9*K9/252 | O9: 0 | P9: =SUM($N$2:N9)
A10: 44939 | B10: TSLQ | C10: TSLA | D10: 0 | E10: 0 | F10: -6277 | G10: -302 | H10: =D10*F10 | I10: =E10*G10 | J10: =H10-I10 | K10: -0.02 | L10: 7281.2951 | M10: -3248.5645 | N10: =-I10*K10/252 | O10: 1 | P10: =SUM($N$2:N10)
A11: 44943 | B11: TSLQ | C11: TSLA | D11: 0 | E11: 0 | F11: -5992 | G11: -371 | H11: =D11*F11 | I11: =E11*G11 | J11: =H11-I11 | K11: -0.02 | L11: -54467.304 | M11: 29132.693 | N11: =-I11*K11/252 | O11: 0 | P11: =SUM($N$2:N11)
A12: 44944 | B12: TSLQ | C12: TSLA | D12: 0 | E12: 0 | F12: -5992 | G12: -371 | H12: =D12*F12 | I12: =E12*G12 | J12: =H12-I12 | K12: -0.02 | L12: 16238.36 | M12: -7432.8618 | N12: =-I12*K12/252 | O12: 0 | P12: =SUM($N$2:N12)
A13: 44945 | B13: TSLQ | C13: TSLA | D13: 0 | E13: 0 | F13: -5992 | G13: -371 | H13: =D13*F13 | I13: =E13*G13 | J13: =H13-I13 | K13: -0.02 | L13: 9647.1237 | M13: -4938.5526 | N13: =-I13*K13/252 | O13: 0 | P13: =SUM($N$2:N13)
... A21: 44957 | B21: TSLQ | C21: TSLA | D21: 0 | E21: 0 | F21: -4374 | G21: -594 | H21: =D21*F21 | I21: =E21*G21 | J21: =H21-I21 | K21: -0.02 | L21: -28693.429 | M21: 16612.857 | N21: =-I21*K21/252 | O21: 0 | P21: =SUM($N$2:N21)

Sheet XBI_LABU
A1: date | B1: etf | C1: under | D1: XBI Price | E1: LABU Price | F1: long_sh | G1: short_sh | H1: long_notional_usd | I1: short_notional_usd | J1: gross_notional_usd | K1: borrow_rate_annual | L1: daily_long_pnl_usd | M1: daily_short_pnl_usd | N1: daily_borrow_cost_usd | O1: is_rebal | P1: cum_borrow_cost_usd
A2: 44929 | B2: LABU | C2: XBI | D2: 81.094872 | E2: 131.40686 | F2: 3382 | G2: -699 | H2: =D2*F2 | I2: =E2*G2 | J2: =H2-I2 | K2: 0.1 | L2: 0 | M2: 0 | N2: =-I2*K2/252 | O2: 1 | P2: =SUM($N$2:N2)
A3: 44930 | B3: LABU | C3: XBI | D3: 82.795746 | E3: 139.26375 | F3: 3382 | G3: -699 | H3: =D3*F3 | I3: =E3*G3 | J3: =H3-I3 | K3: 0.1 | L3: 0 | M3: 0 | N3: =-I3*K3/252 | O3: 0 | P3: =SUM($N$2:N3)
A4: 44931 | B4: LABU | C4: XBI | D4: 82.079575 | E4: 136.12099 | F4: 3382 | G4: -699 | H4: =D4*F4 | I4: =E4*G4 | J4: =H4-I4 | K4: 0.1 | L4: -2422.0912 | M4: 2196.7901 | N4: =-I4*K4/252 | O4: 0 | P4: =SUM($N$2:N4)
A5: 44932 | B5: LABU | C5: XBI | D5: 82.716171 | E5: 138.47806 | F5: 3382 | G5: -699 | H5: =D5*F5 | I5: =E5*G5 | J5: =H5-I5 | K5: 0.1 | L5: 2152.97 | M5: -1647.5926 | N5: =-I5*K5/252 | O5: 1 | P5: =SUM($N$2:N5)
A6: 44935 | B6: LABU | C6: XBI | D6: 80.836258 | E6: 130.42473 | F6: 3382 | G6: -676 | H6: =D6*F6 | I6: =E6*G6 | J6: =H6-I6 | K6: 0.1 | L6: -6357.8669 | M6: 5444.0507 | N6: =-I6*K6/252 | O6: 0 | P6: =SUM($N$2:N6)
A7: 44936 | B7: LABU | C7: XBI | D7: 83.133919 | E7: 140.63872 | F7: 3382 | G7: -676 | H7: =D7*F7 | I7: =E7*G7 | J7: =H7-I7 | K7: 0.1 | L7: 7770.6889 | M7: -6904.6567 | N7: =-I7*K7/252 | O7: 0 | P7: =SUM($N$2:N7)
A8: 44937 | B8: LABU | C8: XBI | D8: 83.929665 | E8: 144.17432 | F8: 3382 | G8: -676 | H8: =D8*F8 | I8: =E8*G8 | J8: =H8-I8 | K8: 0.1 | L8: 2691.2125 | M8: -2390.0648 | N8: =-I8*K8/252 | O8: 0 | P8: =SUM($N$2:N8)
A9: 44938 | B9: LABU | C9: XBI | D9: 87.450775 | E9: 162.0488 | F9: 3382 | G9: -676 | H9: =D9*F9 | I9: =E9*G9 | J9: =H9-I9 | K9: 0.1 | L9: 11908.396 | M9: -12083.149 | N9: =-I9*K9/252 | O9: 0 | P9: =SUM($N$2:N9)
A10: 44939 | B10: LABU | C10: XBI | D10: 87.41098 | E10: 161.65594 | F10: 3382 | G10: -676 | H10: =D10*F10 | I10: =E10*G10 | J10: =H10-I10 | K10: 0.1 | L10: -134.58643 | M10: 265.56848 | N10: =-I10*K10/252 | O10: 1 | P10: =SUM($N$2:N10)
A11: 44943 | B11: LABU | C11: XBI | D11: 86.396431 | E11: 156.9418 | F11: 3391 | G11: -614 | H11: =D11*F11 | I11: =E11*G11 | J11: =H11-I11 | K11: 0.1 | L11: -3440.3365 | M11: 2894.4831 | N11: =-I11*K11/252 | O11: 0 | P11: =SUM($N$2:N11)
A12: 44944 | B12: LABU | C12: XBI | D12: 85.322189 | E12: 150.85271 | F12: 3391 | G12: -614 | H12: =D12*F12 | I12: =E12*G12 | J12: =H12-I12 | K12: 0.1 | L12: -3642.7534 | M12: 3738.705 | N12: =-I12*K12/252 | O12: 0 | P12: =SUM($N$2:N12)
A13: 44945 | B13: LABU | C13: XBI | D13: 84.436943 | E13: 146.33498 | F13: 3391 | G13: -614 | H13: =D13*F13 | I13: =E13*G13 | J13: =H13-I13 | K13: 0.1 | L13: -3001.8701 | M13: 2773.8867 | N13: =-I13*K13/252 | O13: 0 | P13: =SUM($N$2:N13)
... A21: 44957 | B21: LABU | C21: XBI | D21: 88.425529 | E21: 164.01302 | F21: 3537 | G21: -630 | H21: =D21*F21 | I21: =E21*G21 | J21: =H21-I21 | K21: 0.1 | L21: 6332.6095 | M21: -5939.8283 | N21: =-I21*K21/252 | O21: 0 | P21: =SUM($N$2:N21)

Sheet XLE_ERX
A1: date | B1: etf | C1: under | D1: XLE Price | E1: ERX Price | F1: long_sh | G1: short_sh | H1: long_notional_usd | I1: short_notional_usd | J1: gross_notional_usd | K1: borrow_rate_annual | L1: daily_long_pnl_usd | M1: daily_short_pnl_usd | N1: daily_borrow_cost_usd | O1: is_rebal | P1: cum_borrow_cost_usd
A2: 44929 | B2: ERX | C2: XLE | D2: 37.877674 | E2: 56.535763 | F2: 1856 | G2: -625 | H2: =D2*F2 | I2: =E2*G2 | J2: =H2-I2 | K2: 0.12 | L2: 0 | M2: 0 | N2: =-I2*K2/252 | O2: 1 | P2: =SUM($N$2:N2)
A3: 44930 | B3: ERX | C3: XLE | D3: 37.873188 | E3: 56.590691 | F3: 1856 | G3: -625 | H3: =D3*F3 | I3: =E3*G3 | J3: =H3-I3 | K3: 0.12 | L3: 0 | M3: 0 | N3: =-I3*K3/252 | O3: 0 | P3: =SUM($N$2:N3)
A4: 44931 | B4: ERX | C4: XLE | D4: 38.56432 | E4: 58.788033 | F4: 1856 | G4: -625 | H4: =D4*F4 | I4: =E4*G4 | J4: =H4-I4 | K4: 0.12 | L4: 1282.7402 | M4: -1373.3387 | N4: =-I4*K4/252 | O4: 0 | P4: =SUM($N$2:N4)
A5: 44932 | B5: ERX | C5: XLE | D5: 39.295841 | E5: 60.774792 | F5: 1856 | G5: -625 | H5: =D5*F5 | I5: =E5*G5 | J5: =H5-I5 | K5: 0.12 | L5: 1357.7041 | M5: -1241.7245 | N5: =-I5*K5/252 | O5: 1 | P5: =SUM($N$2:N5)
A6: 44935 | B6: ERX | C6: XLE | D6: 39.156723 | E6: 60.426884 | F6: 1856 | G6: -604 | H6: =D6*F6 | I6: =E6*G6 | J6: =H6-I6 | K6: 0.12 | L6: -258.20337 | M6: 210.13644 | N6: =-I6*K6/252 | O6: 0 | P6: =SUM($N$2:N6)
A7: 44936 | B7: ERX | C7: XLE | D7: 39.434967 | E7: 61.2509 | F7: 1856 | G7: -604 | H7: =D7*F7 | I7: =E7*G7 | J7: =H7-I7 | K7: 0.12 | L7: 516.4209 | M7: -497.70601 | N7: =-I7*K7/252 | O7: 0 | P7: =SUM($N$2:N7)
A8: 44937 | B8: ERX | C8: XLE | D8: 39.556141 | E8: 61.543873 | F8: 1856 | G8: -604 | H8: =D8*F8 | I8: =E8*G8 | J8: =H8-I8 | K8: 0.12 | L8: 224.89868 | M8: -176.95543 | N8: =-I8*K8/252 | O8: 0 | P8: =SUM($N$2:N8)
A9: 44938 | B9: ERX | C9: XLE | D9: 40.310108 | E9: 63.887703 | F9: 1856 | G9: -604 | H9: =D9*F9 | I9: =E9*G9 | J9: =H9-I9 | K9: 0.12 | L9: 1399.3633 | M9: -1415.6734 | N9: =-I9*K9/252 | O9: 0 | P9: =SUM($N$2:N9)
A10: 44939 | B10: ERX | C10: XLE | D10: 40.368443 | E10: 64.10743 | F10: 1856 | G10: -604 | H10: =D10*F10 | I10: =E10*G10 | J10: =H10-I10 | K10: 0.12 | L10: 108.26855 | M10: -132.71484 | N10: =-I10*K10/252 | O10: 1 | P10: =SUM($N$2:N10)
A11: 44943 | B11: ERX | C11: XLE | D11: 40.45372 | E11: 64.272217 | F11: 1882 | G11: -596 | H11: =D11*F11 | I11: =E11*G11 | J11: =H11-I11 | K11: 0.12 | L11: 160.49236 | M11: -98.213226 | N11: =-I11*K11/252 | O11: 0 | P11: =SUM($N$2:N11)
A12: 44944 | B12: ERX | C12: XLE | D12: 39.713215 | E12: 62.047417 | F12: 1882 | G12: -596 | H12: =D12*F12 | I12: =E12*G12 | J12: =H12-I12 | K12: 0.12 | L12: -1393.6308 | M12: 1325.9809 | N12: =-I12*K12/252 | O12: 0 | P12: =SUM($N$2:N12)
A13: 44945 | B13: ERX | C13: XLE | D13: 40.206875 | E13: 63.411606 | F13: 1882 | G13: -596 | H13: =D13*F13 | I13: =E13*G13 | J13: =H13-I13 | K13: 0.12 | L13: 929.06807 | M13: -813.05673 | N13: =-I13*K13/252 | O13: 0 | P13: =SUM($N$2:N13)
... A21: 44957 | B21: ERX | C21: XLE | D21: 40.35947 | E21: 63.649647 | F21: 1969 | G21: -617 | H21: =D21*F21 | I21: =E21*G21 | J21: =H21-I21 | K21: 0.12 | L21: 698.10027 | M21: -570.548 | N21: =-I21*K21/252 | O21: 0 | P21: =SUM($N$2:N21)

Sheet XOP_GUSH
A1: date | B1: etf | C1: under | D1: XOP Price | E1: GUSH Price | F1: long_sh | G1: short_sh | H1: long_notional_usd | I1: short_notional_usd | J1: gross_notional_usd | K1: borrow_rate_annual | L1: daily_long_pnl_usd | M1: daily_short_pnl_usd | N1: daily_borrow_cost_usd | O1: is_rebal | P1: cum_borrow_cost_usd
A2: 44929 | B2: GUSH | C2: XOP | D2: 118.34798 | E2: 29.709955 | F2: 3057 | G2: -6059 | H2: =D2*F2 | I2: =E2*G2 | J2: =H2-I2 | K2: -0.01 | L2: 0 | M2: 0 | N2: =-I2*K2/252 | O2: 1 | P2: =SUM($N$2:N2)
A3: 44930 | B3: GUSH | C3: XOP | D3: 118.76312 | E3: 29.891546 | F3: 3057 | G3: -6059 | H3: =D3*F3 | I3: =E3*G3 | J3: =H3-I3 | K3: -0.01 | L3: 0 | M3: 0 | N3: =-I3*K3/252 | O3: 0 | P3: =SUM($N$2:N3)
A4: 44931 | B4: GUSH | C4: XOP | D4: 118.93842 | E4: 29.974298 | F4: 3057 | G4: -6059 | H4: =D4*F4 | I4: =E4*G4 | J4: =H4-I4 | K4: -0.01 | L4: 535.87061 | M4: -501.39575 | N4: =-I4*K4/252 | O4: 0 | P4: =SUM($N$2:N4)
A5: 44932 | B5: GUSH | C5: XOP | D5: 121.37404 | E5: 31.254648 | F5: 3057 | G5: -6059 | H5: =D5*F5 | I5: =E5*G5 | J5: =H5-I5 | K5: -0.01 | L5: 7445.7 | M5: -7757.639 | N5: =-I5*K5/252 | O5: 1 | P5: =SUM($N$2:N5)
A6: 44935 | B6: GUSH | C6: XOP | D6: 122.61028 | E6: 31.859188 | F6: 3057 | G6: -6059 | H6: =D6*F6 | I6: =E6*G6 | J6: =H6-I6 | K6: -0.01 | L6: 3779.1752 | M6: -3662.9071 | N6: =-I6*K6/252 | O6: 0 | P6: =SUM($N$2:N6)
A7: 44936 | B7: GUSH | C7: XOP | D7: 123.02546 | E7: 32.029285 | F7: 3057 | G7: -6059 | H7: =D7*F7 | I7: =E7*G7 | J7: =H7-I7 | K7: -0.01 | L7: 1269.2176 | M7: -1030.6199 | N7: =-I7*K7/252 | O7: 0 | P7: =SUM($N$2:N7)
A8: 44937 | B8: GUSH | C8: XOP | D8: 123.98493 | E8: 32.534981 | F8: 3057 | G8: -6059 | H8: =D8*F8 | I8: =E8*G8 | J8: =H8-I8 | K8: -0.01 | L8: 2933.1079 | M8: -3064.0081 | N8: =-I8*K8/252 | O8: 0 | P8: =SUM($N$2:N8)
A9: 44938 | B9: GUSH | C9: XOP | D9: 127.64754 | E9: 34.442852 | F9: 3057 | G9: -6059 | H9: =D9*F9 | I9: =E9*G9 | J9: =H9-I9 | K9: -0.01 | L9: 11196.584 | M9: -11559.792 | N9: =-I9*K9/252 | O9: 0 | P9: =SUM($N$2:N9)
A10: 44939 | B10: GUSH | C10: XOP | D10: 128.32101 | E10: 34.815243 | F10: 3057 | G10: -6059 | H10: =D10*F10 | I10: =E10*G10 | J10: =H10-I10 | K10: -0.01 | L10: 2058.8197 | M10: -2256.3155 | N10: =-I10*K10/252 | O10: 1 | P10: =SUM($N$2:N10)
A11: 44943 | B11: GUSH | C11: XOP | D11: 128.92996 | E11: 35.074982 | F11: 3048 | G11: -5589 | H11: =D11*F11 | I11: =E11*G11 | J11: =H11-I11 | K11: -0.01 | L11: 1856.0728 | M11: -1451.6808 | N11: =-I11*K11/252 | O11: 0 | P11: =SUM($N$2:N11)
A12: 44944 | B12: GUSH | C12: XOP | D12: 126.4113 | E12: 33.753269 | F12: 3048 | G12: -5589 | H12: =D12*F12 | I12: =E12*G12 | J12: =H12-I12 | K12: -0.01 | L12: -7676.8802 | M12: 7387.0511 | N12: =-I12*K12/252 | O12: 0 | P12: =SUM($N$2:N12)
A13: 44945 | B13: GUSH | C13: XOP | D13: 128.87457 | E13: 35.031315 | F13: 3048 | G13: -5589 | H13: =D13*F13 | I13: =E13*G13 | J13: =H13-I13 | K13: -0.01 | L13: 7508.0533 | M13: -7142.9972 | N13: =-I13*K13/252 | O13: 0 | P13: =SUM($N$2:N13)
... A21: 44957 | B21: GUSH | C21: XOP | D21: 130.05548 | E21: 35.576096 | F21: 3135 | G21: -5607 | H21: =D21*F21 | I21: =E21*G21 | J21: =H21-I21 | K21: -0.01 | L21: 6189.4437 | M21: -6096.2949 | N21: =-I21*K21/252 | O21: 0 | P21: =SUM($N$2:N21)

Sheet portfolio_ledger
A1: date | B1: total_long_notional_usd | C1: benchmark_rate_annual | D1: margin_spread_annual | E1: effective_margin_rate_annual | F1: daily_portfolio_margin_usd | G1: daily_txn_pairs_sum_usd | H1: book_daily_txn_cost_usd | I1: book_daily_net_margin_usd | J1: book_txn_plus_net_margin_usd | K1: sum_pair_daily_net_pnl_usd | L1: net_after_portfolio_margin_and_pair_txn_usd | M1: fund_daily_pnl_usd | N1: diff_model_net_minus_fund_usd
A2: 44929 | B2: =SUMIFS(ALL_PAIRS!$H:$H,ALL_PAIRS!$A:$A,$A2) | C2: =AVERAGEIFS(ALL_PAIRS!$Q:$Q,ALL_PAIRS!$A:$A,$A2) | D2: 0.0045 | E2: =C2+D2 | F2: =B2*E2/252 | G2: =SUMIFS(ALL_PAIRS!$R:$R,ALL_PAIRS!$A:$A,$A2) | H2: 52426.705 | I2: 0 | J2: =H2+I2 | K2: =SUMIFS(ALL_PAIRS!$S:$S,ALL_PAIRS!$A:$A,$A2) | L2: =K2-F2-G2 | M2: -52427.373 | N2: 52577.452
A3: 44930 | B3: =SUMIFS(ALL_PAIRS!$H:$H,ALL_PAIRS!$A:$A,$A3) | C3: =AVERAGEIFS(ALL_PAIRS!$Q:$Q,ALL_PAIRS!$A:$A,$A3) | D3: 0.0045 | E3: =C3+D3 | F3: =B3*E3/252 | G3: =SUMIFS(ALL_PAIRS!$R:$R,ALL_PAIRS!$A:$A,$A3) | H3: 0 | I3: 0 | J3: =H3+I3 | K3: =SUMIFS(ALL_PAIRS!$S:$S,ALL_PAIRS!$A:$A,$A3) | L3: =K3-F3-G3 | M3: 258659.35 | N3: -258478.66
A4: 44931 | B4: =SUMIFS(ALL_PAIRS!$H:$H,ALL_PAIRS!$A:$A,$A4) | C4: =AVERAGEIFS(ALL_PAIRS!$Q:$Q,ALL_PAIRS!$A:$A,$A4) | D4: 0.0045 | E4: =C4+D4 | F4: =B4*E4/252 | G4: =SUMIFS(ALL_PAIRS!$R:$R,ALL_PAIRS!$A:$A,$A4) | H4: 0 | I4: 0 | J4: =H4+I4 | K4: =SUMIFS(ALL_PAIRS!$S:$S,ALL_PAIRS!$A:$A,$A4) | L4: =K4-F4-G4 | M4: -177017.7 | N4: 3177.9897
A5: 44932 | B5: =SUMIFS(ALL_PAIRS!$H:$H,ALL_PAIRS!$A:$A,$A5) | C5: =AVERAGEIFS(ALL_PAIRS!$Q:$Q,ALL_PAIRS!$A:$A,$A5) | D5: 0.0045 | E5: =C5+D5 | F5: =B5*E5/252 | G5: =SUMIFS(ALL_PAIRS!$R:$R,ALL_PAIRS!$A:$A,$A5) | H5: 574.64786 | I5: 0 | J5: =H5+I5 | K5: =SUMIFS(ALL_PAIRS!$S:$S,ALL_PAIRS!$A:$A,$A5) | L5: =K5-F5-G5 | M5: 137451.17 | N5: 3826.1758
A6: 44935 | B6: =SUMIFS(ALL_PAIRS!$H:$H,ALL_PAIRS!$A:$A,$A6) | C6: =AVERAGEIFS(ALL_PAIRS!$Q:$Q,ALL_PAIRS!$A:$A,$A6) | D6: 0.0045 | E6: =C6+D6 | F6: =B6*E6/252 | G6: =SUMIFS(ALL_PAIRS!$R:$R,ALL_PAIRS!$A:$A,$A6) | H6: 0 | I6: 0 | J6: =H6+I6 | K6: =SUMIFS(ALL_PAIRS!$S:$S,ALL_PAIRS!$A:$A,$A6) | L6: =K6-F6-G6 | M6: 162639.96 | N6: 3438.2704
A7: 44936 | B7: =SUMIFS(ALL_PAIRS!$H:$H,ALL_PAIRS!$A:$A,$A7) | C7: =AVERAGEIFS(ALL_PAIRS!$Q:$Q,ALL_PAIRS!$A:$A,$A7) | D7: 0.0045 | E7: =C7+D7 | F7: =B7*E7/252 | G7: =SUMIFS(ALL_PAIRS!$R:$R,ALL_PAIRS!$A:$A,$A7) | H7: 0 | I7: 0 | J7: =H7+I7 | K7: =SUMIFS(ALL_PAIRS!$S:$S,ALL_PAIRS!$A:$A,$A7) | L7: =K7-F7-G7 | M7: 196102.83 | N7: 3647.9234
A8: 44937 | B8: =SUMIFS(ALL_PAIRS!$H:$H,ALL_PAIRS!$A:$A,$A8) | C8: =AVERAGEIFS(ALL_PAIRS!$Q:$Q,ALL_PAIRS!$A:$A,$A8) | D8: 0.0045 | E8: =C8+D8 | F8: =B8*E8/252 | G8: =SUMIFS(ALL_PAIRS!$R:$R,ALL_PAIRS!$A:$A,$A8) | H8: 0 | I8: 0 | J8: =H8+I8 | K8: =SUMIFS(ALL_PAIRS!$S:$S,ALL_PAIRS!$A:$A,$A8) | L8: =K8-F8-G8 | M8: 71240.65 | N8: 3707.2612
A9: 44938 | B9: =SUMIFS(ALL_PAIRS!$H:$H,ALL_PAIRS!$A:$A,$A9) | C9: =AVERAGEIFS(ALL_PAIRS!$Q:$Q,ALL_PAIRS!$A:$A,$A9) | D9: 0.0045 | E9: =C9+D9 | F9: =B9*E9/252 | G9: =SUMIFS(ALL_PAIRS!$R:$R,ALL_PAIRS!$A:$A,$A9) | H9: 0 | I9: 0 | J9: =H9+I9 | K9: =SUMIFS(ALL_PAIRS!$S:$S,ALL_PAIRS!$A:$A,$A9) | L9: =K9-F9-G9 | M9: 110098.36 | N9: 3882.8924
A10: 44939 | B10: =SUMIFS(ALL_PAIRS!$H:$H,ALL_PAIRS!$A:$A,$A10) | C10: =AVERAGEIFS(ALL_PAIRS!$Q:$Q,ALL_PAIRS!$A:$A,$A10) | D10: 0.0045 | E10: =C10+D10 | F10: =B10*E10/252 | G10: =SUMIFS(ALL_PAIRS!$R:$R,ALL_PAIRS!$A:$A,$A10) | H10: 6627.6473 | I10: 0 | J10: =H10+I10 | K10: =SUMIFS(ALL_PAIRS!$S:$S,ALL_PAIRS!$A:$A,$A10) | L10: =K10-F10-G10 | M10: 95583.98 | N10: 10625.19
A11: 44943 | B11: =SUMIFS(ALL_PAIRS!$H:$H,ALL_PAIRS!$A:$A,$A11) | C11: =AVERAGEIFS(ALL_PAIRS!$Q:$Q,ALL_PAIRS!$A:$A,$A11) | D11: 0.0045 | E11: =C11+D11 | F11: =B11*E11/252 | G11: =SUMIFS(ALL_PAIRS!$R:$R,ALL_PAIRS!$A:$A,$A11) | H11: 0 | I11: 0 | J11: =H11+I11 | K11: =SUMIFS(ALL_PAIRS!$S:$S,ALL_PAIRS!$A:$A,$A11) | L11: =K11-F11-G11 | M11: 121405.74 | N11: 3424.8415
A12: 44944 | B12: =SUMIFS(ALL_PAIRS!$H:$H,ALL_PAIRS!$A:$A,$A12) | C12: =AVERAGEIFS(ALL_PAIRS!$Q:$Q,ALL_PAIRS!$A:$A,$A12) | D12: 0.0045 | E12: =C12+D12 | F12: =B12*E12/252 | G12: =SUMIFS(ALL_PAIRS!$R:$R,ALL_PAIRS!$A:$A,$A12) | H12: 0 | I12: 0 | J12: =H12+I12 | K12: =SUMIFS(ALL_PAIRS!$S:$S,ALL_PAIRS!$A:$A,$A12) | L12: =K12-F12-G12 | M12: -124165.81 | N12: 3424.9608
A13: 44945 | B13: =SUMIFS(ALL_PAIRS!$H:$H,ALL_PAIRS!$A:$A,$A13) | C13: =AVERAGEIFS(ALL_PAIRS!$Q:$Q,ALL_PAIRS!$A:$A,$A13) | D13: 0.0045 | E13: =C13+D13 | F13: =B13*E13/252 | G13: =SUMIFS(ALL_PAIRS!$R:$R,ALL_PAIRS!$A:$A,$A13) | H13: 0 | I13: 0 | J13: =H13+I13 | K13: =SUMIFS(ALL_PAIRS!$S:$S,ALL_PAIRS!$A:$A,$A13) | L13: =K13-F13-G13 | M13: -41244.9 | N13: 3376.4235
... A21: 44957 | B21: =SUMIFS(ALL_PAIRS!$H:$H,ALL_PAIRS!$A:$A,$A21) | C21: =AVERAGEIFS(ALL_PAIRS!$Q:$Q,ALL_PAIRS!$A:$A,$A21) | D21: 0.0045 | E21: =C21+D21 | F21: =B21*E21/252 | G21: =SUMIFS(ALL_PAIRS!$R:$R,ALL_PAIRS!$A:$A,$A21) | H21: 0 | I21: 0 | J21: =H21+I21 | K21: =SUMIFS(ALL_PAIRS!$S:$S,ALL_PAIRS!$A:$A,$A21) | L21: =K21-F21-G21 | M21: 174193.43 | N21: 3493.4642
