Workbook

Sheet monthly_attribution
A1: portfolio | B1: month | C1: benchmark_rate | D1: long_trading_pnl | E1: short_trading_pnl | F1: txn_costs | G1: borrow_cost | H1: margin_interest | I1: total_costs | J1: nav_change_pnl | K1: net_pnl_pre_fees | L1: lp_mgmt_fee | M1: lp_perf_fee | N1: lp_total_fee | O1: net_pnl
A2: Diamond Creek Fund | B2: 2023-01 | C2: 0.0432 | D2: 6175027.7 | E2: -4928985.3 | F2: 13517.74 | G2: 10515.613 | H2: 53870.58 | I2: =F2+G2+H2 -> 77903.933 | J2: 1429967.5 | K2: 1437504 | L2: 0 | M2: 0 | N2: 0 | O2: 1437504
A3: Diamond Creek Fund | B3: 2023-02 | C3: 0.0457 | D3: 1025707.2 | E3: -462037.04 | F3: 2805.43 | G3: 10769.092 | H3: 59607.03 | I3: =F3+G3+H3 -> 73181.552 | J3: 490488.65 | K3: 493073.7 | L3: 0 | M3: 0 | N3: 0 | O3: 493073.7
A4: Diamond Creek Fund | B4: 2023-03 | C4: 0.0482 | D4: 4277165.1 | E4: -3408038.4 | F4: 14776.34 | G4: 13421.048 | H4: 76475.04 | I4: =F4+G4+H4 -> 104672.43 | J4: 764454.23 | K4: 768483.19 | L4: 45237.77 | M4: 408189.7 | N4: 453427.46 | O4: 315055.72
A5: Diamond Creek Fund | B5: 2023-04 | C5: 0.0481 | D5: -377747.97 | E5: 522858.91 | F5: 1740.26 | G5: 10789.463 | H5: 68438.98 | I5: =F5+G5+H5 -> 80968.703 | J5: 64142.23 | K5: 64480.28 | L5: 63841.36 | M5: 0 | N5: 63841.36 | O5: 638.92
A6: Diamond Creek Fund | B6: 2023-05 | C6: 0.0507 | D6: 4177917.5 | E6: -3020017.6 | F6: 2089.41 | G6: 12230.27 | H6: 86318.25 | I6: =F6+G6+H6 -> 100637.93 | J6: 1057261.9 | K6: 1062834.1 | L6: 43073.54 | M6: 0 | N6: 43073.54 | O6: 1019760.6
A7: Diamond Creek Fund | B7: 2023-06 | C7: 0.0507 | D7: 3089532.9 | E7: -2282650.7 | F7: 12564.01 | G7: 13833.451 | H7: 88452.93 | I7: =F7+G7+H7 -> 114850.39 | J7: 692031.87 | K7: 695679.14 | L7: 57322.62 | M7: 270504.61 | N7: 327827.23 | O7: 367851.91
A8: Diamond Creek Fund | B8: 2023-07 | C8: 0.0532 | D8: 4655036.3 | E8: -3620840.6 | F8: 9830.95 | G8: 15332.878 | H8: 90902.94 | I8: =F8+G8+H8 -> 116066.77 | J8: 918128.95 | K8: 922967.83 | L8: 128950.78 | M8: 0 | N8: 128950.78 | O8: 794017.05
A9: Diamond Creek Fund | B9: 2023-08 | C9: 0.0532 | D9: -1574959.5 | E9: 1462011.9 | F9: 7841 | G9: 15891.272 | H9: 103551.64 | I9: =F9+G9+H9 -> 127283.91 | J9: -240231.48 | K9: -241497.58 | L9: 0 | M9: 0 | N9: 0 | O9: -241497.58
A10: Diamond Creek Fund | B10: 2023-09 | C10: 0.0532 | D10: -2650360.6 | E10: 2388335.4 | F10: 12320.72 | G10: 14686.008 | H10: 98059.74 | I10: =F10+G10+H10 -> 125066.47 | J10: -383889.78 | K10: -385913.02 | L10: 8086 | M10: 4221.88 | N10: 12307.87 | O10: -398220.9
A11: Diamond Creek Fund | B11: 2023-10 | C11: 0.0532 | D11: -1089517.1 | E11: 1165627.6 | F11: 5396.02 | G11: 15364.674 | H11: 103212.84 | I11: =F11+G11+H11 -> 123973.53 | J11: -47077.07 | K11: -47325.19 | L11: 65562.95 | M11: 0 | N11: 65562.95 | O11: -112888.14
A12: Diamond Creek Fund | B12: 2023-11 | C12: 0.0532 | D12: 6656629.5 | E12: -5301135.2 | F12: 16198.97 | G12: 20683.13 | H12: 102585.16 | I12: =F12+G12+H12 -> 139467.26 | J12: 1216027 | K12: 1222435.9 | L12: 89308.72 | M12: 0 | N12: 89308.72 | O12: 1133127.2
A13: Diamond Creek Fund | B13: 2023-12 | C13: 0.0532 | D13: 3916545.9 | E13: -2929109.4 | F13: 11133.69 | G13: 22636.559 | H13: 102413.47 | I13: =F13+G13+H13 -> 136183.72 | J13: 851252.78 | K13: 855739.2 | L13: 71379.02 | M13: 321039.07 | N13: 392418.09 | O13: 463321.1
... A40: Diamond Creek Fund | B40: 2026-03 | C40: 0.0364 | D40: -2959797.9 | E40: 4491161.7 | F40: 48535.58 | G40: 251282.01 | H40: 142831.65 | I40: =F40+G40+H40 -> 442649.24 | J40: 1088678.5 | K40: 1094416.2 | L40: 206092.37 | M40: 0 | N40: 206092.37 | O40: 888323.84
D41: =SUM(D2:D40) -> 67525037 | E41: =SUM(E2:E40) -> -41496889 | F41: =SUM(F2:F40) -> 977946.19 | G41: =SUM(G2:G40) -> 2426923.6 | H41: =SUM(H2:H40) -> 4109596.1 | I41: =SUM(I2:I40) -> 7514465.9 | J41: =SUM(J2:J40) -> 18794552 | K41: =SUM(K2:K40) -> 18893606 | ... O41: =SUM(O2:O40) -> 13336588
D44: =D41+E41 -> 26028148

Sheet summary
A1: portfolio | B1: long_trading_pnl | C1: short_trading_pnl | D1: txn_costs | E1: borrow_cost | F1: margin_interest | G1: total_costs | H1: net_pnl_pre_fees | I1: lp_mgmt_fee | J1: lp_perf_fee | K1: lp_total_fee | L1: net_pnl
A2: Diamond Creek Fund | B2: =SUM(monthly_attribution!D2:D40) -> 67525037 | C2: =SUM(monthly_attribution!E2:E40) -> -41496889 | D2: =SUM(monthly_attribution!F2:F40) -> 977946.19 | E2: =SUM(monthly_attribution!G2:G40) -> 2426923.6 | F2: =SUM(monthly_attribution!H2:H40) -> 4109596.1 | G2: =D2+E2+F2 -> 7514465.9 | H2: 18893606 | I2: 3381944.5 | J2: 2175072.9 | K2: =I2+J2 -> 5557017.4 | L2: =H2-K2 -> 13336588

Sheet daily_pnl_active_pairs
A1: date | B1: nav | C1: daily_pnl_usd | D1: long_trading_pnl | E1: short_trading_pnl | F1: gross_pnl | G1: txn_costs_paid | H1: borrow_and_short_sale_rebate_net | I1: net_margin_paid_excess_interest | J1: net_pnl_before_lp_fees | K1: active_pairs
A2: 44929 | B2: 9947572.6 | C2: 0 | D2: 0 | E2: 0 | F2: 0 | G2: 0 | H2: 0 | I2: 0 | J2: 0 | K2: 26
A3: 44930 | B3: 10206232 | C3: 258659.35 | D3: 0 | E3: 0 | F3: 0 | G3: 0 | H3: 532.02 | I3: 2637.71 | J3: -3169.73 | K3: 26
A4: 44931 | B4: 10029214 | C4: -177017.7 | D4: -824044.52 | E4: 650063.51 | F4: -173981.01 | G4: 0 | H4: 489.23 | I4: 2547.46 | J4: -177017.7 | K4: 26
A5: 44932 | B5: 10166665 | C5: 137451.17 | D5: 646792.41 | E5: -505655.12 | F5: 141137.3 | G5: 574.62 | H5: 489.51 | I5: 2622 | J5: 137451.17 | K5: 26
A6: 44933 | B6: 10329305 | C6: 162639.96 | D6: 910388.44 | E6: -744494.67 | F6: 165893.78 | G6: 0 | H6: 525.08 | I6: 2728.74 | J6: 162639.96 | K6: 26
A7: 44934 | B7: 10525408 | C7: 196102.83 | D7: 886063.34 | E7: -686566.02 | F7: 199497.32 | G7: 0 | H7: 573.67 | I7: 2820.82 | J7: 196102.83 | K7: 26
A8: 44935 | B8: 10596649 | C8: 71240.65 | D8: 469232.37 | E8: -394528.99 | F8: 74703.38 | G8: 0 | H8: 584.09 | I8: 2878.63 | J8: 71240.65 | K8: 26
A9: 44936 | B9: 10706747 | C9: 110098.36 | D9: 734780.23 | E9: -621088.81 | F9: 113691.42 | G9: 0 | H9: 629.99 | I9: 2963.06 | J9: 110098.36 | K9: 26
A10: 44937 | B10: 10802331 | C10: 95583.98 | D10: 590186.82 | E10: -484292.3 | F10: 105894.52 | G10: 6629.08 | H10: 654.23 | I10: 3027.23 | J10: 95583.98 | K10: 26
A11: 44938 | B11: 10923737 | C11: 121405.74 | D11: 415688.78 | E11: -290939.13 | F11: 124749.65 | G11: 0 | H11: 555.17 | I11: 2788.74 | J11: 121405.74 | K11: 26
A12: 44939 | B12: 10799571 | C12: -124165.81 | D12: -642691.13 | E12: 521765.16 | F12: -120925.97 | G12: 0 | H12: 522.54 | I12: 2717.31 | J12: -124165.81 | K12: 26
A13: 44940 | B13: 10758326 | C13: -41244.9 | D13: -116327 | E13: 78305.37 | F13: -38021.63 | G13: 0 | H13: 520.33 | I13: 2702.94 | J13: -41244.9 | K13: 26
... A814: 45741 | B814: 28742124 | C814: 275898.08 | D814: 4563052 | E814: -4268497.6 | F814: 294554.38 | G814: 0 | H814: 11810.82 | I814: 6845.48 | J814: 275898.08 | K814: 266
